{"author": "frzqp3814396 (GGYY)", "category": "Gossiping", "title": "[問卦] 甜死人的飲料誰在買==", "date": "Wed Apr 17 20:43:20 2024", "content": ["台灣人越來越喜歡無糖飲料可是超商還是可以看到很多超級甜的飲料尤其調味乳那類的超恐怖…這些東西到底賣給誰啊！？有沒有八卦？-----Sent from JPTT on my iPhone--"], "post_comment": [{"comment_author": "bboywhite", "comment_date": ["04/17", "20:43"], "comment_content": "不是我"}, {"comment_author": "justice2008", "comment_date": ["04/17", "20:43"], "comment_content": "我啊 我都買手搖果汁全糖"}, {"comment_author": "OPPAISuki", "comment_date": ["04/17", "20:43"], "comment_content": "小孩 小時候都喝超甜"}, {"comment_author": "bonfferoni", "comment_date": ["04/17", "20:44"], "comment_content": "台男"}, {"comment_author": "OPPAISuki", "comment_date": ["04/17", "20:44"], "comment_content": "長大 開始越喝越淡"}, {"comment_author": "koexe", "comment_date": ["04/17", "20:45"], "comment_content": "糖是毒品"}, {"comment_author": "baek6415", "comment_date": ["04/17", "20:46"], "comment_content": "小時候的你不就在喝，這就是答案"}, {"comment_author": "etiennechiu", "comment_date": ["04/17", "20:50"], "comment_content": "台 南 人"}, {"comment_author": "funkD", "comment_date": ["04/17", "20:50"], "comment_content": "南部人"}, {"comment_author": "opm", "comment_date": ["04/17", "21:12"], "comment_content": "台南人啊"}, {"comment_author": "a3221715", "comment_date": ["04/17", "21:27"], "comment_content": "可樂一直都很甜 但就一直喝"}, {"comment_author": "a3221715", "comment_date": ["04/17", "21:27"], "comment_content": "買手搖基本上微糖以下都比便利商店糖少"}, {"comment_author": "a3221715", "comment_date": ["04/17", "21:27"], "comment_content": "很多"}, {"comment_author": "a3221715", "comment_date": ["04/17", "21:28"], "comment_content": "化工飲料真的很恐怖 糖都加免錢的"}]}
