{"author": "noleese (諾理斯)", "category": "Gossiping", "title": "[問卦] 看到缺電不會很氣嗎?", "date": "Thu Apr 18 14:03:18 2024", "content": ["先不管原本答應不會沒電不會漲價這堆事情當時核能發電毀掉不用就真的很傻B第一 核廢料明明簽好約可以丟北韓這樣廢料就不需要放你家了好嗎第二 針對第一點 韓國跟原能會干預誰屌原能會 我們又沒簽約美國靠腰的話不然你也叫美國簽碳排放的合約看看韓國就更不用理他了第三戰爭危險?中共比你還怕你家核能爆掉影響海洋然後現在核能快沒了電價漲了 最近還有電力差點不夠專家預估這波要花一度電17塊去買（有新聞可以查）所以我說到底在幹嘛本末倒置核能不用燃油燃氣大爆用綠能還像阿斗一樣倒底?有人有掛嗎--"], "post_comment": [{"comment_author": "tmgl", "comment_date": ["04/18", "14:03"], "comment_content": "啊你就選不贏智障啊"}, {"comment_author": "hiphopmei", "comment_date": ["04/18", "14:04"], "comment_content": "生氣有用嗎=="}, {"comment_author": "milk250", "comment_date": ["04/18", "14:04"], "comment_content": "氣能怎樣  就是投不贏信徒啊"}, {"comment_author": "jasonkey123", "comment_date": ["04/18", "14:04"], "comment_content": "現在這麼悲憤,投票時又縮回去了..."}, {"comment_author": "snow3804", "comment_date": ["04/18", "14:04"], "comment_content": "你113幾%"}, {"comment_author": "GGGHILL", "comment_date": ["04/18", "14:05"], "comment_content": "結論就是台灣智障太多"}, {"comment_author": "milk250", "comment_date": ["04/18", "14:05"], "comment_content": "你最多只能詛咒死忠仔家裡停電停到電器都"}, {"comment_author": "Mei5566", "comment_date": ["04/18", "14:05"], "comment_content": "雌彘教徒"}, {"comment_author": "milk250", "comment_date": ["04/18", "14:05"], "comment_content": "壞掉  不過即使如此他們還是會相信台灣不"}, {"comment_author": "tctv2002", "comment_date": ["04/18", "14:05"], "comment_content": "台灣要爆掉  死忠的才會覺醒"}, {"comment_author": "milk250", "comment_date": ["04/18", "14:05"], "comment_content": "缺電"}, {"comment_author": "tctv2002", "comment_date": ["04/18", "14:05"], "comment_content": "就跟日本泡沫 人民才不會炒房一樣"}, {"comment_author": "whiteadam", "comment_date": ["04/18", "14:06"], "comment_content": "缺ㄉㄜ"}, {"comment_author": "OPPAISuki", "comment_date": ["04/18", "14:06"], "comment_content": "台灣人就傻好騙阿 自己選擇的 民主阿"}, {"comment_author": "su4vu6", "comment_date": ["04/18", "14:09"], "comment_content": "為啥會生氣==? 沒有任何道理產生這情緒阿"}, {"comment_author": "lmu0837", "comment_date": ["04/18", "14:10"], "comment_content": "我家還沒停到電，不氣不氣"}, {"comment_author": "mk5520", "comment_date": ["04/18", "14:10"], "comment_content": "爆掉的分水嶺不知道在哪，趕快讓40%醒"}, {"comment_author": "bebehome", "comment_date": ["04/18", "14:15"], "comment_content": "公園超多阿伯每天在生氣，你可以加入"}, {"comment_author": "rossikao", "comment_date": ["04/18", "14:20"], "comment_content": "40%仔低能太多 你問的問題他們不想知道"}, {"comment_author": "john011043", "comment_date": ["04/18", "15:45"], "comment_content": "最慘的大概是真的政黨輪替了民進黨肯"}, {"comment_author": "john011043", "comment_date": ["04/18", "15:45"], "comment_content": "定會瘋狂砲轟為什麼台灣缺電"}]}
