{"author": "xzcb2008 (可愛老娘變態貓貓=.=)", "category": "Gossiping", "title": "[問卦] =.= 後來你娶了理想 我嫁了門對戶當？！", "date": "Sat Apr 13 18:28:06 2024", "content": ["後來你娶了理想我嫁給了戶對門當愛與不愛又何妨從前說無懼山海用九百九十九張車票換有你的未來只要你在後來你把我歸還人海哭著說欠我的未來下輩子再愛這算是渣女被放生嗎？有八卦嗎？男生娶了理想是什麼意思--"], "post_comment": [{"comment_author": "james732", "comment_date": ["04/13", "18:28"], "comment_content": "就是我跟felixden結婚的意思"}, {"comment_author": "ncc5566", "comment_date": ["04/13", "18:28"], "comment_content": "太早"}, {"comment_author": "ncc5566", "comment_date": ["04/13", "18:29"], "comment_content": "這首叫\"從前說\" 抖音少看點好嗎"}, {"comment_author": "fp737", "comment_date": ["04/13", "18:29"], "comment_content": "你HDSM嗎?"}, {"comment_author": "Marle", "comment_date": ["04/13", "18:29"], "comment_content": "這首全民party超多人唱"}, {"comment_author": "wafiea708", "comment_date": ["04/13", "18:29"], "comment_content": "我放下所有回憶來成全你的愛情 的意思"}, {"comment_author": "vV070413", "comment_date": ["04/13", "18:29"], "comment_content": "後來你娶了門當戶對 我嫁給了理想 才對"}, {"comment_author": "boy1031", "comment_date": ["04/13", "18:30"], "comment_content": "理想=未成年"}, {"comment_author": "bill403777", "comment_date": ["04/13", "18:30"], "comment_content": "阿肥的符號很不理想 我的才門當戶對=="}, {"comment_author": "hmt17", "comment_date": ["04/13", "18:30"], "comment_content": "太早"}, {"comment_author": "xzcb2008", "comment_date": ["04/13", "18:33"], "comment_content": "一樓讚"}, {"comment_author": "xzcb2008", "comment_date": ["04/13", "18:33"], "comment_content": "9樓看著我=.="}, {"comment_author": "Himiko9975", "comment_date": ["04/13", "18:33"], "comment_content": "噁心死了 什麼爛歌"}, {"comment_author": "vV070413", "comment_date": ["04/13", "18:34"], "comment_content": "曾經我在車站等了誰三個小時"}, {"comment_author": "xzcb2008", "comment_date": ["04/13", "18:34"], "comment_content": "我也覺得是iwin"}, {"comment_author": "xzcb2008", "comment_date": ["04/13", "18:35"], "comment_content": "=.=vv仔"}, {"comment_author": "ym60606", "comment_date": ["04/13", "18:35"], "comment_content": "一個被動女生對男生無病伸吟的破歌"}, {"comment_author": "xzcb2008", "comment_date": ["04/13", "18:35"], "comment_content": "有故事？"}, {"comment_author": "k385476916", "comment_date": ["04/13", "18:36"], "comment_content": "不要再說了 要哭了"}, {"comment_author": "ym60606", "comment_date": ["04/13", "18:36"], "comment_content": "沒什麼故事 那爛故事寫在歌詞裡"}, {"comment_author": "vV070413", "comment_date": ["04/13", "18:36"], "comment_content": "有啊XD"}, {"comment_author": "felixden", "comment_date": ["04/13", "18:38"], "comment_content": "我娶Gura =="}, {"comment_author": "k385476916", "comment_date": ["04/13", "18:38"], "comment_content": "你在做夢啦"}, {"comment_author": "zorro1111", "comment_date": ["04/13", "18:39"], "comment_content": "恭喜723跟鯊魚煙老闆"}, {"comment_author": "samm3320", "comment_date": ["04/13", "18:59"], "comment_content": "她假得門當戶對也沒虧"}, {"comment_author": "longkiss0618", "comment_date": ["04/13", "19:09"], "comment_content": "這首讚"}, {"comment_author": "viorc", "comment_date": ["04/13", "19:49"], "comment_content": "這首的詞仔細聽會發現很爛而且前後矛盾不"}, {"comment_author": "viorc", "comment_date": ["04/13", "19:49"], "comment_content": "知所云"}, {"comment_author": "xzcb2008", "comment_date": ["04/13", "20:04"], "comment_content": "剛下班=.=別吵"}, {"comment_author": "christopherl", "comment_date": ["04/13", "22:59"], "comment_content": "這首歌描述一對有年齡差的情侶，結"}, {"comment_author": "christopherl", "comment_date": ["04/13", "22:59"], "comment_content": "果被親朋好友、網軍台女一直罵男的"}, {"comment_author": "christopherl", "comment_date": ["04/13", "22:59"], "comment_content": "戀童癖，男的只好娶一個老太婆當成"}, {"comment_author": "christopherl", "comment_date": ["04/13", "23:00"], "comment_content": "治療戀童癖，女的被家長帶回家禁足"}, {"comment_author": "christopherl", "comment_date": ["04/13", "23:00"], "comment_content": "，女的終日以淚洗面"}, {"comment_author": "minami77", "comment_date": ["04/14", "02:41"], "comment_content": "爛詞"}]}
