{"simple_date": " 4/11", "title": "[問卦] 我叫小胖777", "category": "問卦", "author": "MeiHS (簽名檔詳見 其他版晃到，)", "explicity_date": "Thu Apr 11 01:45:24 2024", "content": ["小時候歷史課本有教到 鄭和七次下西洋,船艦大到可以把海盜船撞沉,每次都上萬人出航航跡遠達東非,可是除了帶回一些獅子外 好像也沒啥重大利益?..鄭和下西洋的利益何在?鄭和再努力一點,可以到地中海或葡萄牙嗎?--", "--"], "post_comment": [{"comment_author": "aOOOOOOOOO", "comment_date": ["04/2X", "2N:G2"], "comment_content": "給果凍->更奴化   超棒"}, {"comment_author": "aOOOOOOOOO", "comment_date": ["04/2X", "2N:G3"], "comment_content": "七八年級糞鳥土箸9成不是輪斑94低薪蚊組"}, {"comment_author": "scores", "comment_date": ["04/11", "01:45"], "comment_content": "說不定是找他遺失的雞雞"}, {"comment_author": "darkbrigher", "comment_date": ["04/11", "01:47"], "comment_content": "傳說是去尋找建文帝 所以後來judy一"}, {"comment_author": "darkbrigher", "comment_date": ["04/11", "01:47"], "comment_content": "死 海圖燒了 船放著爛"}, {"comment_author": "edison", "comment_date": ["04/11", "01:49"], "comment_content": "鞏固皇權正統,就像中共處心機率要把"}, {"comment_author": "owlonoak", "comment_date": ["04/11", "01:49"], "comment_content": "這就是中國以農立國而非以商立國的結果"}, {"comment_author": "invidia", "comment_date": ["04/11", "01:49"], "comment_content": "大外宣"}, {"comment_author": "edison", "comment_date": ["04/11", "01:50"], "comment_content": "中華民國消滅"}, {"comment_author": "owlonoak", "comment_date": ["04/11", "01:50"], "comment_content": "中國的國際觀只有宗主與朝貢的關係"}, {"comment_author": "owlonoak", "comment_date": ["04/11", "01:50"], "comment_content": "沒有貿易與殖民的觀念"}, {"comment_author": "owlonoak", "comment_date": ["04/11", "01:51"], "comment_content": "沒有這個觀念 就算鄭和先發現美洲 中國"}, {"comment_author": "owlonoak", "comment_date": ["04/11", "01:51"], "comment_content": "也不會變成日不落國"}, {"comment_author": "eric61446", "comment_date": ["04/11", "01:53"], "comment_content": "西班牙 葡萄牙 英國利益很大的"}, {"comment_author": "eric61446", "comment_date": ["04/11", "01:54"], "comment_content": "香料 白銀"}, {"comment_author": "zien0223", "comment_date": ["04/11", "01:57"], "comment_content": "judy要的是萬國來朝的虛榮心 不然殺侄篡"}, {"comment_author": "zien0223", "comment_date": ["04/11", "01:57"], "comment_content": "位的黑歷史怎麼掩蓋"}, {"comment_author": "AkaiSola", "comment_date": ["04/11", "02:02"], "comment_content": "他走的是沿著陸地的舊航道"}, {"comment_author": "AkaiSola", "comment_date": ["04/11", "02:03"], "comment_content": "還帶了一堆胡椒回國，導致朝廷乾脆把胡"}, {"comment_author": "AkaiSola", "comment_date": ["04/11", "02:03"], "comment_content": "椒當作俸祿發給官員"}, {"comment_author": "darkbrigher", "comment_date": ["04/11", "02:07"], "comment_content": "judy真的開了個壞頭 之後他兒子或是"}, {"comment_author": "darkbrigher", "comment_date": ["04/11", "02:08"], "comment_content": "其他親王一狗票想著造反"}, {"comment_author": "mirrorlee", "comment_date": ["04/11", "02:09"], "comment_content": "國內的明史研究真的該更新了 中國那邊"}, {"comment_author": "mirrorlee", "comment_date": ["04/11", "02:10"], "comment_content": "已經有不少學者提出鄭和下西洋帶來的貿"}, {"comment_author": "mirrorlee", "comment_date": ["04/11", "02:11"], "comment_content": "易利益之大適足以讓judy多次對外戰爭"}, {"comment_author": "mirrorlee", "comment_date": ["04/11", "02:13"], "comment_content": "修運河 遷都 編永樂大典 而不是單單為"}, {"comment_author": "mirrorlee", "comment_date": ["04/11", "02:13"], "comment_content": "面子跟虛無的找建文帝"}, {"comment_author": "darkbrigher", "comment_date": ["04/11", "02:14"], "comment_content": "所以為何三寶艦隊不繼續 反而禁海"}, {"comment_author": "darkbrigher", "comment_date": ["04/11", "02:15"], "comment_content": "你知道朝貢每次都要回禮價值更多的賞"}, {"comment_author": "darkbrigher", "comment_date": ["04/11", "02:16"], "comment_content": "賜嗎 一堆阿貓阿狗商人冒充使節"}, {"comment_author": "xex999", "comment_date": ["04/11", "02:20"], "comment_content": "實際上是朱棣派去找建文帝的"}, {"comment_author": "cocojohn111", "comment_date": ["04/11", "02:29"], "comment_content": "沒那麼複雜 實際上是被他老爹搞得紙"}, {"comment_author": "cocojohn111", "comment_date": ["04/11", "02:29"], "comment_content": "幣坑了 幾乎是為了貨幣 想找白銀礦"}, {"comment_author": "cocojohn111", "comment_date": ["04/11", "02:30"], "comment_content": "搞銀本位 最後貿易雖然賺錢但沒到日"}, {"comment_author": "cocojohn111", "comment_date": ["04/11", "02:30"], "comment_content": "本或南美洲根本找不到"}, {"comment_author": "mirrorlee", "comment_date": ["04/11", "02:30"], "comment_content": "你可能要先搞清楚是誰讓下西洋終止的"}, {"comment_author": "mirrorlee", "comment_date": ["04/11", "02:30"], "comment_content": "在此之前可以先去弄懂有明一朝官員多出"}, {"comment_author": "mirrorlee", "comment_date": ["04/11", "02:31"], "comment_content": "自何省 官方主導對外貿易對那些省的影"}, {"comment_author": "mirrorlee", "comment_date": ["04/11", "02:32"], "comment_content": "響最大 這樣你就會有一個完整的脈絡接"}, {"comment_author": "mirrorlee", "comment_date": ["04/11", "02:32"], "comment_content": "到明朝沿海為何倭寇清剿不完的現象"}, {"comment_author": "darkbrigher", "comment_date": ["04/11", "02:44"], "comment_content": "說了半天根本無法解釋為何不繼續"}, {"comment_author": "mirrorlee", "comment_date": ["04/11", "02:55"], "comment_content": "都給你開頭線索了 自己不去做功課 真當"}, {"comment_author": "mirrorlee", "comment_date": ["04/11", "02:56"], "comment_content": "我有收你學費嗎"}, {"comment_author": "mirrorlee", "comment_date": ["04/11", "02:57"], "comment_content": "今天心情好 再給你一個線索去做功課吧"}, {"comment_author": "mirrorlee", "comment_date": ["04/11", "02:58"], "comment_content": "明朝倭寇組成 真倭多還是假倭多 假倭"}, {"comment_author": "mirrorlee", "comment_date": ["04/11", "02:58"], "comment_content": "又多是出於哪幾個省"}, {"comment_author": "nicholassys", "comment_date": ["04/11", "03:07"], "comment_content": "一樣是遠航 為什麼東西方的成就差那"}, {"comment_author": "nicholassys", "comment_date": ["04/11", "03:08"], "comment_content": "麼多？"}, {"comment_author": "jungi1126", "comment_date": ["04/11", "09:48"], "comment_content": "這明明有漫畫版。這樣背又沒創意。又固"}, {"comment_author": "jungi1126", "comment_date": ["04/11", "09:48"], "comment_content": "步自封。"}, {"comment_author": "jungi1126", "comment_date": ["04/11", "09:50"], "comment_content": "這不就是大國崛起一大套DVD嗎......"}]}
