{"author": "Dinenger (低能兒)", "category": "Gossiping", "title": "[問卦] 為什麼不用蘆葦當吸管就好？", "date": "Fri Apr 19 00:50:54 2024", "content": ["塑膠的不要用紙的也不要用鐵的用久了不好清洗會有重金屬溶出還容易藏污納垢吃出毛病那為什麼不去割蘆葦來當吸管就好？最天然無污染--"], "post_comment": [{"comment_author": "fantasyth", "comment_date": ["04/19", "00:51"], "comment_content": "太貴"}, {"comment_author": "sam810626", "comment_date": ["04/19", "00:51"], "comment_content": "不用吸管就好"}, {"comment_author": "shirleyEchi", "comment_date": ["04/19", "00:52"], "comment_content": "珍奶怎麼吸"}, {"comment_author": "johnson2726", "comment_date": ["04/19", "00:52"], "comment_content": "有人會在蘆葦草堆尿尿"}, {"comment_author": "justice2008", "comment_date": ["04/19", "00:53"], "comment_content": "拉肚子你要負責嗎???"}, {"comment_author": "meblessme", "comment_date": ["04/19", "00:53"], "comment_content": "首先，有機物容易腐爛發酵，無法大量"}, {"comment_author": "orze04", "comment_date": ["04/19", "00:53"], "comment_content": "會掉削"}, {"comment_author": "meblessme", "comment_date": ["04/19", "00:53"], "comment_content": "長期保存，而且太細無法吸任何料"}, {"comment_author": "justice2008", "comment_date": ["04/19", "00:53"], "comment_content": "防腐保存期限怎辦???"}, {"comment_author": "justice2008", "comment_date": ["04/19", "00:53"], "comment_content": "塑膠放十幾年不會壞 反觀"}, {"comment_author": "orze04", "comment_date": ["04/19", "00:54"], "comment_content": "麥桿 蘆葦桿 稻草乾都會分解出屑屑"}, {"comment_author": "justice2008", "comment_date": ["04/19", "00:54"], "comment_content": "你就不要剛好吸到米酵菌酸=="}, {"comment_author": "xeins", "comment_date": ["04/19", "00:54"], "comment_content": "之前越南有蒲草吸管 不過不知道為什麼沒有"}, {"comment_author": "xeins", "comment_date": ["04/19", "00:54"], "comment_content": "被採用"}, {"comment_author": "SAMMY728", "comment_date": ["04/19", "01:01"], "comment_content": "有啊，台灣有品牌再做蒲草吸管。"}, {"comment_author": "xeins", "comment_date": ["04/19", "01:05"], "comment_content": "有啊 我還沒在星巴克或麥當勞看到他們的產"}, {"comment_author": "xeins", "comment_date": ["04/19", "01:05"], "comment_content": "品 還是台北才有店家用？"}, {"comment_author": "jimmy0316", "comment_date": ["04/19", "01:08"], "comment_content": "為什麼不去學特異功能就好了"}, {"comment_author": "jason45698", "comment_date": ["04/19", "01:10"], "comment_content": "吸管越用越長 最後你就能吹百鳥朝鳳"}, {"comment_author": "Takhisis", "comment_date": ["04/19", "01:48"], "comment_content": "窩喜歡看人表演用湯匙喝珍奶"}, {"comment_author": "PowerGeMOS", "comment_date": ["04/19", "09:12"], "comment_content": "你直播肛門搾甘蔗也蠻天然的，支持！"}, {"comment_author": "PowerGeMOS", "comment_date": ["04/19", "09:14"], "comment_content": ""}]}
