{"author": "dennistao (不住心齋橋的心齋橋哥)", "category": "Gossiping", "title": "[問卦] 雲豹跟00940哪個最能代表台灣?", "date": "Fri Apr 19 11:52:06 2024", "content": ["上班股票兩頭賺的各位安安阿~~啊我就那個心齋橋哥啦台灣還是有蠻多自己的特有種，但有些復育很成功，例如櫻花鉤吻鮭有些就已經滅絕，如台灣雲豹", "如圖所示，很可愛啦雖說是絕種，但因為是本土特有種很能代表台灣吧另一個就是最近被討論到爆炸的台灣價值00940大家覺得這兩個哪一個比較能代表台灣阿瓜?--"], "post_comment": [{"comment_author": "highyes", "comment_date": ["04/19", "11:52"], "comment_content": "党說了算 = =！"}, {"comment_author": "VoV", "comment_date": ["04/19", "11:53"], "comment_content": "一個騙韭菜,一個有黨好安心"}, {"comment_author": "gime0226", "comment_date": ["04/19", "11:53"], "comment_content": "雲豹40%  00940 60%"}, {"comment_author": "livehouse", "comment_date": ["04/19", "11:53"], "comment_content": "貪污代表"}, {"comment_author": "lionpass", "comment_date": ["04/19", "11:56"], "comment_content": "唯一支持雲豹"}, {"comment_author": "toolittle", "comment_date": ["04/19", "11:58"], "comment_content": "雲豹  我準備好了"}, {"comment_author": "flshoyo", "comment_date": ["04/19", "12:04"], "comment_content": "差那麼多  一個賺爛一個賠爛"}, {"comment_author": "au4g3wk4k", "comment_date": ["04/19", "12:04"], "comment_content": "一個只能特定人士買 一個可以40%買 CC"}, {"comment_author": "AWPER", "comment_date": ["04/19", "12:12"], "comment_content": "一個割韭菜。另一個割國營，國營再割韭菜"}, {"comment_author": "liker1412", "comment_date": ["04/19", "12:54"], "comment_content": "問就是民進黨 只能是民進黨"}]}
