{"author": "ubang (長得醜卻想得美)", "category": "Gossiping", "title": "[問卦] 美國是烏鴉嘴還是神預測", "date": "Sun Apr 14 08:11:53 2024", "content": ["如題啦美國前幾天就說伊朗要參戰了之前也說俄國要開打這樣是要算烏鴉嘴嗎說開打就開打還是神預測有沒有卦--"], "post_comment": [{"comment_author": "dustree", "comment_date": ["04/14", "08:13"], "comment_content": "情報網跟間諜幹嘛用的?"}, {"comment_author": "vul3vmp4", "comment_date": ["04/14", "08:13"], "comment_content": "有當地情報人士 還有衛星監控"}, {"comment_author": "gx8759121", "comment_date": ["04/14", "08:14"], "comment_content": "印度神童說的，美國信了，懂?"}, {"comment_author": "poisonB", "comment_date": ["04/14", "08:15"], "comment_content": "伊朗先跟美國講的 叫美國人不要反擊"}, {"comment_author": "palindromes", "comment_date": ["04/14", "08:16"], "comment_content": "你不知道伊朗總理有跟國民講嗎"}, {"comment_author": "bole", "comment_date": ["04/14", "08:17"], "comment_content": "就美國害的啊"}, {"comment_author": "fvbwyrmsc", "comment_date": ["04/14", "08:17"], "comment_content": "以為CIA 吃屎的嗎"}, {"comment_author": "krousxchen", "comment_date": ["04/14", "08:18"], "comment_content": "所以中國才要反間諜"}, {"comment_author": "like3100", "comment_date": ["04/14", "08:21"], "comment_content": "開始擔憂2027前武力犯台的情報…."}, {"comment_author": "firemothra", "comment_date": ["04/14", "08:25"], "comment_content": "2027不要不信"}, {"comment_author": "choh", "comment_date": ["04/14", "08:26"], "comment_content": "美國可以監聽到全世界元首的通話"}, {"comment_author": "firemothra", "comment_date": ["04/14", "08:26"], "comment_content": "到時候美國廠跟日本廠差不多都穩定產"}, {"comment_author": "firemothra", "comment_date": ["04/14", "08:26"], "comment_content": "出晶片了"}, {"comment_author": "vul3vmp4", "comment_date": ["04/14", "08:26"], "comment_content": "2027年穩打的啦。逢甲碟仙和美國情報都"}, {"comment_author": "vul3vmp4", "comment_date": ["04/14", "08:26"], "comment_content": "這麼說了。光是看到哥布林黨現在一直在"}, {"comment_author": "vul3vmp4", "comment_date": ["04/14", "08:26"], "comment_content": "島內瘋狂開設台積電的廠就知道 想拿台積"}, {"comment_author": "vul3vmp4", "comment_date": ["04/14", "08:27"], "comment_content": "電當護身符 讓中共的攻擊會成為國際譴責"}, {"comment_author": "vul3vmp4", "comment_date": ["04/14", "08:27"], "comment_content": "因為全世界都需要台積電"}, {"comment_author": "firemothra", "comment_date": ["04/14", "08:28"], "comment_content": "台灣只剩晶片可以拿來情勒全世界了"}, {"comment_author": "Yohachan", "comment_date": ["04/14", "08:37"], "comment_content": "你以為美國是躺在家裡隨便發廢文？"}, {"comment_author": "ultraccs", "comment_date": ["04/14", "08:48"], "comment_content": "要打以色列 要先跟美國報備吧"}, {"comment_author": "vul3vmp4", "comment_date": ["04/14", "08:50"], "comment_content": "都撕破臉了 要開打了 還要先報備讓對方"}, {"comment_author": "vul3vmp4", "comment_date": ["04/14", "08:50"], "comment_content": "有準備？ 怎麼這麼仁慈"}, {"comment_author": "idealman", "comment_date": ["04/14", "08:51"], "comment_content": "因為打之前都跟美國報備過了"}, {"comment_author": "shala", "comment_date": ["04/14", "08:53"], "comment_content": "就不是偷襲啊，跟以色列不同格調"}, {"comment_author": "ggttoo", "comment_date": ["04/14", "09:11"], "comment_content": "CiA"}, {"comment_author": "ouabain", "comment_date": ["04/14", "10:39"], "comment_content": "只有你相信老共"}, {"comment_author": "sheep79119", "comment_date": ["04/14", "11:26"], "comment_content": "是情報"}]}
