{"author": "yoyodiy (廢文心得文大師)", "category": "Gossiping", "title": "[問卦] 有人買40年老公寓沒整修直接入住的嗎？", "date": "Thu Apr 18 13:07:28 2024", "content": ["嗨大家午安  本魯失業11年自耕農本魯老婆去年換屋  把10年前買的老公寓賣掉 轉成七年套房當初買公寓屋齡30年  是第一次交易 所以浴室敲掉重作室內裝潢重啦電線花了60萬左右後來賣掉時  是社區新高價賣出  但對面的前一年賣 也是第一次交易只賣1/2價買到的買家就直接入住  防水也沒重作  電線也沒重拉買40年公寓都沒裝潢直接入住的多嗎？是常態?--", "40年老公寓  浴室防水幾乎都是失效的吧"], "post_comment": [{"comment_author": "bboywhite", "comment_date": ["04/18", "13:07"], "comment_content": "前一手整理沒幾年 不過反映在價格了"}, {"comment_author": "link4517", "comment_date": ["04/18", "13:08"], "comment_content": "沒任何瑕疵為什麼要整理？ 家具擺一擺直"}, {"comment_author": "link4517", "comment_date": ["04/18", "13:08"], "comment_content": "接入住"}, {"comment_author": "Roooz", "comment_date": ["04/18", "13:08"], "comment_content": "看自己的財力ㄅ"}, {"comment_author": "Nevhir", "comment_date": ["04/18", "13:09"], "comment_content": "很少 基本上如果自己要長住都會重弄 除非"}, {"comment_author": "Nevhir", "comment_date": ["04/18", "13:09"], "comment_content": "短期"}, {"comment_author": "chigo520", "comment_date": ["04/18", "13:09"], "comment_content": "很多啊 那種租老公寓的不就是"}, {"comment_author": "Nevhir", "comment_date": ["04/18", "13:10"], "comment_content": "最重要是沒錢"}, {"comment_author": "alaokj", "comment_date": ["04/18", "13:10"], "comment_content": "公寓地點先講再討論"}, {"comment_author": "luciffar", "comment_date": ["04/18", "13:11"], "comment_content": "921把老房子都搖爛了 不修理怎麼住"}, {"comment_author": "alaokj", "comment_date": ["04/18", "13:11"], "comment_content": "大安區公寓一狗票、你整理一下比新三蘆還"}, {"comment_author": "alaokj", "comment_date": ["04/18", "13:12"], "comment_content": "好住，又沒公設"}, {"comment_author": "dan5120", "comment_date": ["04/18", "13:12"], "comment_content": "40年自住一定要整理== 除非簡單用租人"}, {"comment_author": "alaokj", "comment_date": ["04/18", "13:12"], "comment_content": "如果是什麼蛋殼區就不要浪費錢了"}, {"comment_author": "whitenoise", "comment_date": ["04/18", "13:13"], "comment_content": "40年建議重整理，不然等到家人、傢俱"}, {"comment_author": "whitenoise", "comment_date": ["04/18", "13:13"], "comment_content": "都安置好後再整修會相～當～麻煩，光"}, {"comment_author": "whitenoise", "comment_date": ["04/18", "13:13"], "comment_content": "是想就不想動了"}, {"comment_author": "alaokj", "comment_date": ["04/18", "13:13"], "comment_content": "隨便隨緣、邊住邊賣"}, {"comment_author": "calmness26", "comment_date": ["04/18", "13:13"], "comment_content": "自住的話要整理吧"}, {"comment_author": "lmu0837", "comment_date": ["04/18", "13:14"], "comment_content": "完了，居然賣社區新高價而不是半價賣，"}, {"comment_author": "andre9", "comment_date": ["04/18", "13:16"], "comment_content": "很恐怖 千萬要水電整理 哪天燒起來都不知"}, {"comment_author": "gust0985", "comment_date": ["04/18", "13:18"], "comment_content": "40年怎可能不整理直接住，別鬧了"}, {"comment_author": "gust0985", "comment_date": ["04/18", "13:19"], "comment_content": "除非你是買人家整理完的，有出示單據證"}, {"comment_author": "gust0985", "comment_date": ["04/18", "13:19"], "comment_content": "明那種"}, {"comment_author": "alex00089", "comment_date": ["04/18", "13:19"], "comment_content": "油漆也算？"}, {"comment_author": "o523874", "comment_date": ["04/18", "13:21"], "comment_content": "用電量要不要算一下.14平方線也只能50A。"}, {"comment_author": "o523874", "comment_date": ["04/18", "13:21"], "comment_content": "都不換會很暖"}, {"comment_author": "u87803170", "comment_date": ["04/18", "13:23"], "comment_content": "一定要整理 漏水  還有電線走火"}, {"comment_author": "u87803170", "comment_date": ["04/18", "13:23"], "comment_content": "都很可怕"}, {"comment_author": "andy2011", "comment_date": ["04/18", "13:50"], "comment_content": "空屋不整理好塞滿了才要整理就是豬了"}, {"comment_author": "ringohejia", "comment_date": ["04/19", "00:35"], "comment_content": "拿去租就沒人有意見了 :)"}]}
