{"author": "stewartqq (涼a)", "category": "Gossiping", "title": "[新聞] 與台智光解約 北市警局洽備援系統", "date": "Wed Apr 17 12:38:45 2024", "content": ["1.媒體來源:udn聯合新聞網2.記者署名:記者楊正海3.完整新聞標題:與台智光解約 北市警局洽備援系統4.完整新聞內文: 台灣智慧光網爭議持續延燒，由於收取費率高，", "，下周二前台智光要有回應。北市資訊局長趙式隆昨天在市議會工作報告時指出，若經催告對方仍不理，未來將以1761費率先付款；但議員認為太瞎、", "，並且到財建委員會專案報告。資訊局表示，針對解除子約後的備援系統，警察局正與中華電信洽談；北市法務局表示，發文給台智光解約，是合約中給台智光的行政救濟及說明主張權利，未解約前，台智光仍要持續提供服務。議員簡舒培說，市府發文台智光說明期限15天，之後市府再依民法催告，但市府仍以1761費率先付款，還是繼續用台智光、繼續讓台智光賺。議員陳炳甫質問，市政府的解約進度？包括子約、母約、備案討論，有沒有開始接洽？相信很多業者磨刀霍霍想要承接，市府也才會有和台智光談判的武器，市府應該找好備援，以解約後強制斷訊，備援可馬上接手。議員林亮君表示，市府與台智光所簽的合約散落在市府局處，其中包含重要的資訊系統，包括大地工程處的土石流觀測影像、消防局派遣系統及托嬰、老福、老人住宅也是使用台智光，若市府要解約，有要求其他局處做好準備？盤點需求嗎？議員洪婉臻也說，", "？公務機關使用台智光占85%，解約後配套呢？資訊局長趙式隆說，主要是警察局的子約先解約，警察局的監視器就占了台智光8成以上，少了這部分，這間公司活不下去。趙式隆表示，目前解除子約主要在警察局，硬體的部分，已持續接洽一些中小型、規模比台智光大、有經驗的業者；上會期，市議會已要求警察局的備援系統，因此已洽詢中華電信，市府也對將基礎建設換成其他業者，預做準備。針對解約部分，趙式隆說，警察局會優先，然後才會是其他局處，若要全部替換，仍有銜接風險。議員林世宗質詢指出，未來傳輸上是否有空窗期？趙式隆說，必須不受影響，要有周全的計畫。5.完整新聞連結 (或短網址)不可用YAHOO、LINE、MSN等轉載媒體:", "6.備註:原來是解除....子約....用標題唬爛?藍綠開始洗地嗆小草吧!!!--"], "post_comment": [{"comment_author": "jkhz", "comment_date": ["04/17", "12:39"], "comment_content": "先說要找誰接管吧，不然罷工就糗了"}, {"comment_author": "svd237", "comment_date": ["04/17", "12:40"], "comment_content": "蔣萬安繼續演戲"}, {"comment_author": "tmgl", "comment_date": ["04/17", "12:40"], "comment_content": "又要幫kmt買單"}, {"comment_author": "sexygnome", "comment_date": ["04/17", "12:41"], "comment_content": "主約不就訂在那邊，可以說不跟他簽就"}, {"comment_author": "sexygnome", "comment_date": ["04/17", "12:41"], "comment_content": "不要嗎"}, {"comment_author": "a8521abcd", "comment_date": ["04/17", "12:43"], "comment_content": "解除子約XD"}, {"comment_author": "pansquarl", "comment_date": ["04/17", "12:43"], "comment_content": "主約不解就繼續讓台智光爽下去啊"}, {"comment_author": "coneflwer", "comment_date": ["04/17", "12:53"], "comment_content": "餵公子吃餅"}, {"comment_author": "driver0811", "comment_date": ["04/17", "12:57"], "comment_content": "雙方都不滿意的約才是好合約"}, {"comment_author": "hkcdc", "comment_date": ["04/17", "13:59"], "comment_content": "看到民眾黨跟綠營 齊跳腳  是不是做對了"}, {"comment_author": "pomelolawod", "comment_date": ["04/17", "14:13"], "comment_content": "解約還顧慮公司營運狀況 真是辛苦捏"}, {"comment_author": "jack7775kimo", "comment_date": ["04/17", "15:10"], "comment_content": "努力幫淡化\"陳重文\",\"郝龍斌\"幾個字"}, {"comment_author": "xu3m4zp", "comment_date": ["04/17", "18:02"], "comment_content": "不管啦 都是子約害人家貪的"}]}
