{"author": "alex1987 (基努李維)", "category": "Gossiping", "title": "[新聞] 備轉不足5％！明潭456儲能水力故障 全台", "date": "Mon Apr 15 21:20:05 2024", "content": ["1.媒體來源:中時電子報2.記者署名:江飛宇3.完整新聞標題:備轉不足5％！明潭456儲能水力故障 全台瀕臨停電4.完整新聞內文:雖然還未進入夏天，但是台灣缺電問題已經全面浮現，今天傍晚的電力供應出現明顯短缺，備轉容量跌至5%以下，已是限電風險的橘燈，而且非常接近偏紅燈。然而，只要沒有出現電網崩潰，政府依然會擺出歲月靜好的態度。現在正處春天尾聲，許多機組仍在歲修，但氣溫已經有時轉熱，所以到了傍晚時分的「二次用電尖峰」時期，最近這陣子屢屢出現備轉電力不足的情況，又以今日(4月15日)特別明顯。根據「電力圖表視覺化」網站，今天下午3點半以後，備轉容量率已低到10%的黃燈線，之後備轉率愈來愈低，到下午4點半已低至6%的橘燈線，並且還在往下探，一度下探5.22%。", "明潭抽蓄電廠4、5、6機在傍晚故障， 全台瀕臨停電。(圖/台電網站)一位 不具名的前線電力工作受訪時表示，其實台電網站的數據，會經過修飾，所以數值上出現5%，但實際狀況往往更糟，可能只剩1%。", "好幾座火力電廠在今天超額定運轉，功率突破100%。(圖/台電網站截圖、合成)今天對台電來說運氣不好的是，做為儲能重任的明潭抽蓄電廠的4、5、6號機，在傍晚出現故障，立即少了720百萬瓦(MW)，這使得其他電廠的負擔更為沉重，甚至已停機的核二廠兩部緊急汽油發電機被迫上線供電，已除役的大林電廠5號機，也在今天下午運轉。更有些火力電廠被迫「燃燒小宇宙」，機組功率超過100%，比如高雄的興達電廠3號機達到101%，4號機功率105%；南部電廠1號機104%、2號機100.3%、3號機更創下106%的驚人紀錄。民營電廠也一樣，海湖燃氣電廠1號機100.8%、2號機100.3%；星元燃氣電廠105%！即使石門水庫儲水量只剩24%，應該好好保留，但是為了支持今晚的電力供應，1號機「水力全開」，發電功率達到96%，真不知這一放水，會增加多少桃園地區的缺水隱患?", "即使石門水庫儲水量只剩24.8%，但為了供電穩定，也硬著頭皮發電了，功率達到96%。(圖/台電、台水)核四廠前廠長王伯輝表示，今天晚上17：50，大潭8號機跳脫，到了18：20，明潭4、5、6號機組也出現跳脫，這總共少了1820百萬瓦(1.82GW)。需知我們現在的白天用電，很大程度都要看天候，因為靠太陽能，但是晚上又沒有光電，使得今天特別慘！該上來的機組全上了，連水情吃緊的石門水庫都用上。除了上述提及的以外，好幾座「環保限制運轉」的機組，在今天都破例「不環保」，它們功率超過90 ％，甚至超過100 ％。王伯輝廠長總結指出，「即使今天下半夜度過難關，但是夜路走多了，總有一天會碰到鬼！我希望台電與經濟部能把今天的情況當成教訓，打破再生能源的迷思，不要把台灣的供電能力，擺在自己不能決定的天氣狀況與太陽的位置！」5.完整新聞連結 (或短網址)不可用YAHOO、LINE、MSN等轉載媒體:", "--"], "post_comment": [{"comment_author": "Mayinggo", "comment_date": ["04/15", "21:20"], "comment_content": "沒問題啦 鄭副院長麗君說台電藏電"}, {"comment_author": "LoveMakeLove", "comment_date": ["04/15", "21:20"], "comment_content": "冷氣16度開起來！"}, {"comment_author": "TZUYIC", "comment_date": ["04/15", "21:20"], "comment_content": "政府說不缺電，是誰在造謠？四月就大缺電"}, {"comment_author": "johnwu", "comment_date": ["04/15", "21:20"], "comment_content": "又要缺水缺電了嗎"}, {"comment_author": "bye2007", "comment_date": ["04/15", "21:21"], "comment_content": "前幾天不是很會吹"}, {"comment_author": "nicoshun", "comment_date": ["04/15", "21:21"], "comment_content": "黨說夠就是夠"}, {"comment_author": "jerrty", "comment_date": ["04/15", "21:21"], "comment_content": "房價繼續漲"}, {"comment_author": "fulongb210f", "comment_date": ["04/15", "21:22"], "comment_content": "催落去，冷氣16度C"}, {"comment_author": "bass17", "comment_date": ["04/15", "21:22"], "comment_content": "今年夏天迎接缺水缺電啦"}, {"comment_author": "luna2000sea", "comment_date": ["04/15", "21:22"], "comment_content": "又在危言聳聽了 停電了嗎"}, {"comment_author": "s6525480", "comment_date": ["04/15", "21:22"], "comment_content": "又在造謠了嗎"}, {"comment_author": "wsdykssj", "comment_date": ["04/15", "21:22"], "comment_content": "耶~四月就能停電超前部署"}, {"comment_author": "justice2008", "comment_date": ["04/15", "21:22"], "comment_content": "別擔心 台灣不缺電"}, {"comment_author": "justice2008", "comment_date": ["04/15", "21:22"], "comment_content": "先開16度壓壓驚"}, {"comment_author": "protoss666", "comment_date": ["04/15", "21:22"], "comment_content": "冷氣16度 開來壓力測試囉"}, {"comment_author": "kelon", "comment_date": ["04/15", "21:22"], "comment_content": "党才借地震證明我們電網強韌 別胡說"}, {"comment_author": "info1994", "comment_date": ["04/15", "21:23"], "comment_content": "石門剩20幾 然後拿來發電"}, {"comment_author": "castorhome", "comment_date": ["04/15", "21:23"], "comment_content": "之後沒下雨不就完了"}, {"comment_author": "WowProctor", "comment_date": ["04/15", "21:23"], "comment_content": "停電先停40%"}, {"comment_author": "neil0611", "comment_date": ["04/15", "21:23"], "comment_content": " "}, {"comment_author": "info1994", "comment_date": ["04/15", "21:23"], "comment_content": "原本為了愛護地球跟荷包我都開28，這幾"}, {"comment_author": "shvzrrsy", "comment_date": ["04/15", "21:23"], "comment_content": "40%的選擇"}, {"comment_author": "info1994", "comment_date": ["04/15", "21:24"], "comment_content": "天我就開24度好了"}, {"comment_author": "NaoGaTsu", "comment_date": ["04/15", "21:24"], "comment_content": "40%和黨說不缺電 繼續挺綠電反核電"}, {"comment_author": "KJK7", "comment_date": ["04/15", "21:24"], "comment_content": "中時不可信"}, {"comment_author": "rwr", "comment_date": ["04/15", "21:24"], "comment_content": "超前補水"}, {"comment_author": "penfan", "comment_date": ["04/15", "21:24"], "comment_content": "還班班有冷氣勒，到時候戶戶都停電"}, {"comment_author": "TZUYIC", "comment_date": ["04/15", "21:24"], "comment_content": "之前一直在吹太陽能、綠能的，人呢？消失"}, {"comment_author": "fp737", "comment_date": ["04/15", "21:24"], "comment_content": "去年好像有護國神潭的新聞耶"}, {"comment_author": "NaoGaTsu", "comment_date": ["04/15", "21:24"], "comment_content": "冷氣開好開滿 政府說不缺電的 沒事兒"}, {"comment_author": "believefate", "comment_date": ["04/15", "21:24"], "comment_content": "40%死忠的搞到缺電又缺水 禍害台灣"}, {"comment_author": "TZUYIC", "comment_date": ["04/15", "21:24"], "comment_content": "了嗎？怎麼都沒看到有人在護航了？"}, {"comment_author": "doig", "comment_date": ["04/15", "21:24"], "comment_content": "才熱一天就要爆了，夏天準備大停電"}, {"comment_author": "clone29", "comment_date": ["04/15", "21:24"], "comment_content": "什麼？藏電拿出來，晚上沒冷氣怎麼活"}, {"comment_author": "fp737", "comment_date": ["04/15", "21:24"], "comment_content": "中部潭水靠您了  護國一下"}, {"comment_author": "godofsex", "comment_date": ["04/15", "21:24"], "comment_content": ""}, {"comment_author": "micro9527", "comment_date": ["04/15", "21:25"], "comment_content": "台積瑟瑟發抖"}, {"comment_author": "maxdi", "comment_date": ["04/15", "21:25"], "comment_content": "好可怕，冷氣吹氣來壓壓驚"}, {"comment_author": "hidebehind", "comment_date": ["04/15", "21:25"], "comment_content": "隨便啦 不真的大停電一次 政府死性不"}, {"comment_author": "djyunjie", "comment_date": ["04/15", "21:25"], "comment_content": "40%先停"}, {"comment_author": "gaupyng1", "comment_date": ["04/15", "21:25"], "comment_content": "訊號來了，開冷氣！"}, {"comment_author": "hidebehind", "comment_date": ["04/15", "21:25"], "comment_content": "會改的"}, {"comment_author": "tokeep", "comment_date": ["04/15", "21:25"], "comment_content": "有在恐嚇人民了"}, {"comment_author": "singernall", "comment_date": ["04/15", "21:26"], "comment_content": "早就選完了啦 在那邊叫什麼"}, {"comment_author": "odaaaaa", "comment_date": ["04/15", "21:26"], "comment_content": "中共同路   嗯~   發電機"}, {"comment_author": "chun47", "comment_date": ["04/15", "21:26"], "comment_content": "照賴神得票率 高的限電 OK吧"}, {"comment_author": "jehow", "comment_date": ["04/15", "21:26"], "comment_content": "棄24小時最穩的核電不用 白癡台灣人"}, {"comment_author": "asdzxc001", "comment_date": ["04/15", "21:26"], "comment_content": "去年聽說景氣不好過關，今年……不好"}, {"comment_author": "asdzxc001", "comment_date": ["04/15", "21:26"], "comment_content": "說，用你的稅金跟工廠買電回來……CC"}, {"comment_author": "zerhbbo78", "comment_date": ["04/15", "21:26"], "comment_content": "反正停了就說小動物搞的就好"}, {"comment_author": "jehow", "comment_date": ["04/15", "21:27"], "comment_content": "重點是還花幾千億蓋好了 真的有夠智障"}, {"comment_author": "bluepahahaha", "comment_date": ["04/15", "21:27"], "comment_content": "很好笑 沒有新的發電廠是怎樣"}, {"comment_author": "doig", "comment_date": ["04/15", "21:27"], "comment_content": "賴導繼續騙"}, {"comment_author": "d8511557", "comment_date": ["04/15", "21:27"], "comment_content": "許多機組仍在歲修.沒事啦"}, {"comment_author": "doig", "comment_date": ["04/15", "21:27"], "comment_content": ""}, {"comment_author": "doig", "comment_date": ["04/15", "21:27"], "comment_content": ""}, {"comment_author": "zephyr105", "comment_date": ["04/15", "21:27"], "comment_content": "2.8還在硬撐 真的勇"}, {"comment_author": "taiwanstrike", "comment_date": ["04/15", "21:27"], "comment_content": "希望硬撐到時候7月直接炸開 大家停"}, {"comment_author": "tenlove", "comment_date": ["04/15", "21:27"], "comment_content": "綠色之後的挑戰來了"}, {"comment_author": "nodefeat", "comment_date": ["04/15", "21:27"], "comment_content": "缺電還是缺腦？"}, {"comment_author": "doig", "comment_date": ["04/15", "21:28"], "comment_content": "民進黨繼續騙人民，缺電還整天台積電"}, {"comment_author": "tonyian", "comment_date": ["04/15", "21:28"], "comment_content": "民進黨垃圾：感謝我們的電路強韌計畫"}, {"comment_author": "taiwanstrike", "comment_date": ["04/15", "21:28"], "comment_content": "看看黨要怎麼樣甩前朝遺毒"}, {"comment_author": "Lumia5566", "comment_date": ["04/15", "21:28"], "comment_content": "開冷氣大賽 壓力測試開始"}, {"comment_author": "d8511557", "comment_date": ["04/15", "21:28"], "comment_content": "蠻好笑的，喊了8年全台停電"}, {"comment_author": "qday", "comment_date": ["04/15", "21:28"], "comment_content": "共媒造謠，冷氣16度開起來"}, {"comment_author": "fony1029", "comment_date": ["04/15", "21:28"], "comment_content": ""}, {"comment_author": "kakalayeah", "comment_date": ["04/15", "21:28"], "comment_content": "EE不喜歡這篇文"}, {"comment_author": "fony1029", "comment_date": ["04/15", "21:28"], "comment_content": ""}, {"comment_author": "jerry5988", "comment_date": ["04/15", "21:28"], "comment_content": "要環保還瘋狂用火力和水利"}, {"comment_author": "fony1029", "comment_date": ["04/15", "21:28"], "comment_content": ""}, {"comment_author": "neoa01", "comment_date": ["04/15", "21:29"], "comment_content": "民進黨能源政策錯誤，禍國殃民，台灣罪人"}, {"comment_author": "TZUYIC", "comment_date": ["04/15", "21:29"], "comment_content": "晚上太陽公公就下班了，你各位還敢開冷氣"}, {"comment_author": "fony1029", "comment_date": ["04/15", "21:29"], "comment_content": ""}, {"comment_author": "Mayinggo", "comment_date": ["04/15", "21:29"], "comment_content": "說個笑話 綠能結果用柴油發電"}, {"comment_author": "daniel1344", "comment_date": ["04/15", "21:29"], "comment_content": "太陽能呢 風電呢 是不是在藏"}, {"comment_author": "penfan", "comment_date": ["04/15", "21:29"], "comment_content": "High(開）.起.來～～～"}, {"comment_author": "j3", "comment_date": ["04/15", "21:29"], "comment_content": "某名言 不關我的事了"}, {"comment_author": "v7q4", "comment_date": ["04/15", "21:29"], "comment_content": ""}, {"comment_author": "godofsex", "comment_date": ["04/15", "21:30"], "comment_content": ""}, {"comment_author": "TZUYIC", "comment_date": ["04/15", "21:30"], "comment_content": "缺電缺到要燒柴油發電，這成本……"}, {"comment_author": "kevinpc", "comment_date": ["04/15", "21:30"], "comment_content": "403地震才大張旗鼓的慶祝能源轉型成功"}, {"comment_author": "kelon", "comment_date": ["04/15", "21:30"], "comment_content": "相信党 今晚超熱有人不想開冷氣的嗎"}, {"comment_author": "kimos", "comment_date": ["04/15", "21:30"], "comment_content": "塔綠班：我感覺這葛廠長肯定是中共同路人"}, {"comment_author": "godofsex", "comment_date": ["04/15", "21:30"], "comment_content": ""}, {"comment_author": "wsdykssj", "comment_date": ["04/15", "21:30"], "comment_content": "石門水庫放水到時缺水好開心~"}, {"comment_author": "zephyr105", "comment_date": ["04/15", "21:31"], "comment_content": "鬼島要實現化了嗎"}, {"comment_author": "ddg1802", "comment_date": ["04/15", "21:31"], "comment_content": "核四前廠長好開心的感覺"}, {"comment_author": "bonfferoni", "comment_date": ["04/15", "21:31"], "comment_content": "雲豹還不出來救援"}, {"comment_author": "ToumaKazusa", "comment_date": ["04/15", "21:31"], "comment_content": "蔡英文當年還帶頭上街遊行用愛發電"}, {"comment_author": "johnnyhsu7", "comment_date": ["04/15", "21:31"], "comment_content": "開個冷氣壓壓驚"}, {"comment_author": "ToumaKazusa", "comment_date": ["04/15", "21:31"], "comment_content": "現在想想真是諷刺啊～"}, {"comment_author": "tatol", "comment_date": ["04/15", "21:31"], "comment_content": "擠電跟擠奶一樣 党擠一擠就有了"}, {"comment_author": "nrezw", "comment_date": ["04/15", "21:31"], "comment_content": "島"}, {"comment_author": "teddy72", "comment_date": ["04/15", "21:31"], "comment_content": "這下真的要缺水了"}, {"comment_author": "atliberty", "comment_date": ["04/15", "21:31"], "comment_content": "前幾天很威的風電怎麼軟腳了？"}, {"comment_author": "bloodmickey", "comment_date": ["04/15", "21:31"], "comment_content": "大家只想聽好消息 你支那同路人嗎"}, {"comment_author": "hlb5828", "comment_date": ["04/15", "21:31"], "comment_content": "老子馬上來幫母豬壓力測試"}, {"comment_author": "lml99", "comment_date": ["04/15", "21:31"], "comment_content": "可以超過100趴不錯阿，所以平常都在混"}, {"comment_author": "goodman5566", "comment_date": ["04/15", "21:31"], "comment_content": "太爽啦 16度C 開起來"}, {"comment_author": "cms6384", "comment_date": ["04/15", "21:32"], "comment_content": "一個電廠停電就大停電 那還打什麼仗"}, {"comment_author": "stationary", "comment_date": ["04/15", "21:32"], "comment_content": "問就是藏電，重電發大財"}, {"comment_author": "DogBe106", "comment_date": ["04/15", "21:32"], "comment_content": "40%：4個不同意"}, {"comment_author": "xpxp123xp", "comment_date": ["04/15", "21:32"], "comment_content": "不是再生能源很猛 靠最不環保的柴油稱?"}, {"comment_author": "godofsex", "comment_date": ["04/15", "21:32"], "comment_content": ""}, {"comment_author": "p784533", "comment_date": ["04/15", "21:32"], "comment_content": "走對的路"}, {"comment_author": "MKIU", "comment_date": ["04/15", "21:33"], "comment_content": "40%優先"}, {"comment_author": "chadhsieh", "comment_date": ["04/15", "21:33"], "comment_content": "短時間內超過額定功率是沒問題的"}, {"comment_author": "disyou", "comment_date": ["04/15", "21:33"], "comment_content": "選貪的人"}, {"comment_author": "atpx4869s", "comment_date": ["04/15", "21:33"], "comment_content": "認知作戰！！認知作戰！！！"}, {"comment_author": "TZUYIC", "comment_date": ["04/15", "21:33"], "comment_content": "說真的，就該讓台灣順勢大停電，人民才會"}, {"comment_author": "doig", "comment_date": ["04/15", "21:33"], "comment_content": ""}, {"comment_author": "TZUYIC", "comment_date": ["04/15", "21:33"], "comment_content": "覺醒投錯人的下場是什麼！"}, {"comment_author": "vingfing", "comment_date": ["04/15", "21:33"], "comment_content": "党：不缺電 準備跳電"}, {"comment_author": "doig", "comment_date": ["04/15", "21:34"], "comment_content": ""}, {"comment_author": "iorijkl", "comment_date": ["04/15", "21:34"], "comment_content": "沒在缺電的，冷氣開起來！"}, {"comment_author": "fallinlove15", "comment_date": ["04/15", "21:34"], "comment_content": "冷氣開好了 等等沒電吹怎麼辦"}, {"comment_author": "retrud", "comment_date": ["04/15", "21:34"], "comment_content": "太陽下班了笑死 漲價是為了不缺電"}, {"comment_author": "rabbit83035", "comment_date": ["04/15", "21:34"], "comment_content": "藏的電拿出來阿!!!"}, {"comment_author": "boss88893", "comment_date": ["04/15", "21:34"], "comment_content": ""}, {"comment_author": "joke3547", "comment_date": ["04/15", "21:35"], "comment_content": "說個笑話，台GG還想在台灣擴廠"}, {"comment_author": "kinnazeen", "comment_date": ["04/15", "21:35"], "comment_content": "幹 再不用核電啊，媽的一群反智用愛發"}, {"comment_author": "kinnazeen", "comment_date": ["04/15", "21:35"], "comment_content": "電"}, {"comment_author": "deann", "comment_date": ["04/15", "21:35"], "comment_content": "石門水庫都沒水了還要放水來水力了"}, {"comment_author": "deann", "comment_date": ["04/15", "21:36"], "comment_content": "發電"}, {"comment_author": "joke3547", "comment_date": ["04/15", "21:36"], "comment_content": "承認台GG是炒房工具吧，低能綠班"}, {"comment_author": "adk147852", "comment_date": ["04/15", "21:36"], "comment_content": "當年爽嗆備轉太多 台電藏電"}, {"comment_author": "BREAKFAST204", "comment_date": ["04/15", "21:37"], "comment_content": "一定是台電藏電 大家別怕"}, {"comment_author": "CentaurM83", "comment_date": ["04/15", "21:37"], "comment_content": "這一定是台灣價值不足的觀點"}, {"comment_author": "CentaurM83", "comment_date": ["04/15", "21:37"], "comment_content": "党都說電網強固"}, {"comment_author": "tonykingtwo", "comment_date": ["04/15", "21:37"], "comment_content": "完全執政的8年 搞爛台灣喜迎統一 讚"}, {"comment_author": "yoyoyo916", "comment_date": ["04/15", "21:37"], "comment_content": "台電把藏的電拿出來不就沒事了"}, {"comment_author": "a29976137", "comment_date": ["04/15", "21:37"], "comment_content": "藏電找到了沒"}, {"comment_author": "ihfreud", "comment_date": ["04/15", "21:38"], "comment_content": "冷氣開起來！"}, {"comment_author": "spending", "comment_date": ["04/15", "21:39"], "comment_content": "真垃圾啊"}, {"comment_author": "XAZA", "comment_date": ["04/15", "21:39"], "comment_content": "可以把藏電拿出來用囉"}, {"comment_author": "appleball200", "comment_date": ["04/15", "21:39"], "comment_content": "笑死"}, {"comment_author": "godofsex", "comment_date": ["04/15", "21:39"], "comment_content": ""}, {"comment_author": "bking", "comment_date": ["04/15", "21:40"], "comment_content": "石門水庫為了發電放水......"}, {"comment_author": "sean477", "comment_date": ["04/15", "21:40"], "comment_content": "不要再藏電了台電"}, {"comment_author": "cisyong", "comment_date": ["04/15", "21:40"], "comment_content": "冷氣全開挺雲豹"}, {"comment_author": "STi2011", "comment_date": ["04/15", "21:41"], "comment_content": "幹 用覽叫發電阿 叫哥布林去幹阿"}, {"comment_author": "s9234032", "comment_date": ["04/15", "21:42"], "comment_content": "台電的電ㄋ"}, {"comment_author": "kkchen", "comment_date": ["04/15", "21:42"], "comment_content": "台灣應該不缺電，藏的電還沒拿出來用，用"}, {"comment_author": "kkchen", "comment_date": ["04/15", "21:42"], "comment_content": "愛發電這是台灣特有的電，也都還沒拿出來"}, {"comment_author": "kkchen", "comment_date": ["04/15", "21:42"], "comment_content": "用。"}, {"comment_author": "shi21", "comment_date": ["04/15", "21:43"], "comment_content": "民進黨說沒有缺電啊"}, {"comment_author": "tonylolz", "comment_date": ["04/15", "21:43"], "comment_content": "中時"}, {"comment_author": "cmcmisgod", "comment_date": ["04/15", "21:43"], "comment_content": "政府說不缺電"}, {"comment_author": "superww", "comment_date": ["04/15", "21:43"], "comment_content": "可憐啊 連快沒水的水庫也被抓來救援"}, {"comment_author": "ytkuang", "comment_date": ["04/15", "21:44"], "comment_content": "呼 還好有放水供電  明天繼續放水吧"}, {"comment_author": "tommy21332", "comment_date": ["04/15", "21:45"], "comment_content": "你各位抗中保台還不快喊起來"}, {"comment_author": "aids893001", "comment_date": ["04/15", "21:45"], "comment_content": "有綠電怕三小"}, {"comment_author": "kit279", "comment_date": ["04/15", "21:45"], "comment_content": "不是不缺電嗎"}, {"comment_author": "Syd", "comment_date": ["04/15", "21:46"], "comment_content": "藏的電該拿出來了吧"}, {"comment_author": "cash0221", "comment_date": ["04/15", "21:46"], "comment_content": "台電藏電啦！"}, {"comment_author": "e04x8", "comment_date": ["04/15", "21:46"], "comment_content": "可不可以快蓋煤炭發電廠啊，怕"}, {"comment_author": "Wkkj", "comment_date": ["04/15", "21:46"], "comment_content": "台積電滾出台灣"}, {"comment_author": "bnnm", "comment_date": ["04/15", "21:46"], "comment_content": ""}, {"comment_author": "vltw5v", "comment_date": ["04/15", "21:47"], "comment_content": "黨說不缺電 不要在那邊造謠"}, {"comment_author": "e04x8", "comment_date": ["04/15", "21:47"], "comment_content": "水都不夠了，還要拿來發電…."}, {"comment_author": "snowangelic", "comment_date": ["04/15", "21:47"], "comment_content": "哈哈哈啊哈"}, {"comment_author": "sm3bp078", "comment_date": ["04/15", "21:47"], "comment_content": "可悲啊  要玩的怎麼緊繃 到底是啥低能"}, {"comment_author": "Freeven", "comment_date": ["04/15", "21:47"], "comment_content": "啊不是有太陽能光電"}, {"comment_author": "picass0607", "comment_date": ["04/15", "21:48"], "comment_content": "冷氣16都跟上！"}, {"comment_author": "justice0616", "comment_date": ["04/15", "21:48"], "comment_content": "冷氣吹落去"}, {"comment_author": "snowangelic", "comment_date": ["04/15", "21:48"], "comment_content": "晚上 冷氣那麼猛喔"}, {"comment_author": "hate56", "comment_date": ["04/15", "21:49"], "comment_content": "這報顯然沒有台灣價值 難怪被針對"}, {"comment_author": "PHXD", "comment_date": ["04/15", "21:49"], "comment_content": "已知用水"}, {"comment_author": "e04x8", "comment_date": ["04/15", "21:49"], "comment_content": "冷氣根本就都還沒開，完蛋了"}, {"comment_author": "tndh", "comment_date": ["04/15", "21:51"], "comment_content": "各位明日請努力 重電全開"}, {"comment_author": "godofsex", "comment_date": ["04/15", "21:51"], "comment_content": ""}, {"comment_author": "ziso", "comment_date": ["04/15", "21:52"], "comment_content": "又在造謠了?台灣不缺電!!!"}, {"comment_author": "WWIII", "comment_date": ["04/15", "21:53"], "comment_content": "功率怎麼不突破兩百"}, {"comment_author": "cloud0829", "comment_date": ["04/15", "21:53"], "comment_content": "藏起來的電還不拿出來？"}, {"comment_author": "cosmite", "comment_date": ["04/15", "21:53"], "comment_content": "可悲"}, {"comment_author": "acolam", "comment_date": ["04/15", "21:53"], "comment_content": "我們台電不缺電 這政府真的很敢講"}, {"comment_author": "sunday0913", "comment_date": ["04/15", "21:54"], "comment_content": "484欠人罰300萬,相信政府相信党,冷"}, {"comment_author": "sunday0913", "comment_date": ["04/15", "21:54"], "comment_content": "氣16度走起"}, {"comment_author": "kissung", "comment_date": ["04/15", "21:55"], "comment_content": ""}, {"comment_author": "sincere77", "comment_date": ["04/15", "21:57"], "comment_content": "覺青塔綠班吹很高的光電跟風電根本廢"}, {"comment_author": "sincere77", "comment_date": ["04/15", "21:57"], "comment_content": "物派不上用場"}, {"comment_author": "chuck5669", "comment_date": ["04/15", "21:57"], "comment_content": "冷氣全天開了 真的熱"}, {"comment_author": "blktree", "comment_date": ["04/15", "21:58"], "comment_content": "身為南部人，我真的很羞恥"}, {"comment_author": "erown45654", "comment_date": ["04/15", "21:58"], "comment_content": "造謠ㄝ~台灣有缺過甚麼?真是身在福中"}, {"comment_author": "erown45654", "comment_date": ["04/15", "21:58"], "comment_content": "不知福"}, {"comment_author": "yao03911", "comment_date": ["04/15", "21:59"], "comment_content": "OK 冷氣開16度"}, {"comment_author": "scum5566", "comment_date": ["04/15", "21:59"], "comment_content": "奇怪了，地震完不是才在吹強韌電網大成"}, {"comment_author": "scum5566", "comment_date": ["04/15", "21:59"], "comment_content": "功??? 40%不覺得丟臉嗎???"}, {"comment_author": "doig", "comment_date": ["04/15", "21:59"], "comment_content": ""}, {"comment_author": "zzzzaaaa", "comment_date": ["04/15", "22:01"], "comment_content": "前幾天政府還在吹地震儲能調動得宜耶，"}, {"comment_author": "zzzzaaaa", "comment_date": ["04/15", "22:01"], "comment_content": "很會爭功喔"}, {"comment_author": "monday0315", "comment_date": ["04/15", "22:03"], "comment_content": "假新聞吧 台灣怎麼可能缺電"}, {"comment_author": "maize602", "comment_date": ["04/15", "22:04"], "comment_content": "哇靠，水庫低水位還放水真猛！"}, {"comment_author": "feijai", "comment_date": ["04/15", "22:04"], "comment_content": "之後就輪到小動物缺了"}, {"comment_author": "imtlow", "comment_date": ["04/15", "22:04"], "comment_content": "那個很厲害的智慧電網呢"}, {"comment_author": "ipadpro2", "comment_date": ["04/15", "22:05"], "comment_content": "石門水庫儲水量只剩24%…"}, {"comment_author": "griffick", "comment_date": ["04/15", "22:05"], "comment_content": "早就選完了，民進黨才不怕大停電"}, {"comment_author": "scum5566", "comment_date": ["04/15", "22:06"], "comment_content": "前幾年台灣百年大旱，一樣有偷放水發電"}, {"comment_author": "chitsaijang", "comment_date": ["04/15", "22:06"], "comment_content": "超越時空的打臉"}, {"comment_author": "scum5566", "comment_date": ["04/15", "22:06"], "comment_content": "喔 供參"}, {"comment_author": "icantsay", "comment_date": ["04/15", "22:06"], "comment_content": "南部人準備好了嗎？ 畢竟是死忠的"}, {"comment_author": "covenant", "comment_date": ["04/15", "22:06"], "comment_content": "40%的選擇 全台灣人來承擔 讚"}, {"comment_author": "ymfx000a", "comment_date": ["04/15", "22:07"], "comment_content": "感謝政府 感謝黨"}, {"comment_author": "ice0101001", "comment_date": ["04/15", "22:07"], "comment_content": "40%的用愛發電"}, {"comment_author": "benoaico", "comment_date": ["04/15", "22:07"], "comment_content": "我投同意 所以我16度開起來"}, {"comment_author": "sunwill34243", "comment_date": ["04/15", "22:07"], "comment_content": "4個不同意"}, {"comment_author": "NCTUFAIWEN", "comment_date": ["04/15", "22:07"], "comment_content": "看到新聞趕緊把冷氣調高到17度幫忙"}, {"comment_author": "meli420ssa", "comment_date": ["04/15", "22:08"], "comment_content": "台電不要藏電"}, {"comment_author": "BraviaX95j", "comment_date": ["04/15", "22:08"], "comment_content": "笑死,飛彈都還沒過來,自己先斷電"}, {"comment_author": "jimmy12332", "comment_date": ["04/15", "22:08"], "comment_content": "太陽：怪我囉？"}, {"comment_author": "skery3188", "comment_date": ["04/15", "22:08"], "comment_content": "太熱了 冷氣怎能不開 用核電打臉綠共"}, {"comment_author": "Amanz", "comment_date": ["04/15", "22:08"], "comment_content": "不要漲價呀，垃圾綠"}, {"comment_author": "aleny", "comment_date": ["04/15", "22:09"], "comment_content": "鄭副院長上任，一定可以找到台電藏的電！"}, {"comment_author": "EulerFormula", "comment_date": ["04/15", "22:09"], "comment_content": "滴屁屁說藏的電勒"}, {"comment_author": "lunenera", "comment_date": ["04/15", "22:10"], "comment_content": "停機除役可以運轉 45歲應該也會教召了"}, {"comment_author": "helloffx", "comment_date": ["04/15", "22:10"], "comment_content": "等等冷氣開18度 壓力測試"}, {"comment_author": "fg008kimo", "comment_date": ["04/15", "22:11"], "comment_content": "40%就是低能兒"}, {"comment_author": "JH10", "comment_date": ["04/15", "22:11"], "comment_content": "UPS股買起來"}, {"comment_author": "playerkilled", "comment_date": ["04/15", "22:11"], "comment_content": "還不快把藏電找出來"}, {"comment_author": "a4102607", "comment_date": ["04/15", "22:11"], "comment_content": "冷氣開爆"}, {"comment_author": "lltools", "comment_date": ["04/15", "22:11"], "comment_content": "40%的腦X樂見"}, {"comment_author": "uller", "comment_date": ["04/15", "22:12"], "comment_content": "40% 出去用愛發電阿 可悲綠共仔"}, {"comment_author": "bigpan", "comment_date": ["04/15", "22:12"], "comment_content": "民進黨可以說太陽是中共同路人 40%會相信"}, {"comment_author": "dovepacket", "comment_date": ["04/15", "22:13"], "comment_content": "韌性電力   任性電力"}, {"comment_author": "yujuismylove", "comment_date": ["04/15", "22:13"], "comment_content": "嗯嗯！我開冷氣了"}, {"comment_author": "marke18", "comment_date": ["04/15", "22:14"], "comment_content": "民退党無能"}, {"comment_author": "imkp", "comment_date": ["04/15", "22:14"], "comment_content": "重啟個p"}, {"comment_author": "utomaya", "comment_date": ["04/15", "22:14"], "comment_content": "UPS開起來 不然硬碟要卦了"}, {"comment_author": "peterball", "comment_date": ["04/15", "22:14"], "comment_content": "上網造謠的電很充足啊"}, {"comment_author": "joe821122", "comment_date": ["04/15", "22:15"], "comment_content": "冷氣16度還在運轉啊 誰說沒電"}, {"comment_author": "acergame5", "comment_date": ["04/15", "22:16"], "comment_content": "16度開起來"}, {"comment_author": "JonnyJostar", "comment_date": ["04/15", "22:16"], "comment_content": "冷氣開下去 爽的累"}, {"comment_author": "Mradult", "comment_date": ["04/15", "22:17"], "comment_content": "又在恐嚇人民，是還有5%餘裕好嗎"}, {"comment_author": "ibanes", "comment_date": ["04/15", "22:17"], "comment_content": "40趴喜迎缺水缺電"}, {"comment_author": "ibetitisnot", "comment_date": ["04/15", "22:17"], "comment_content": "又再造謠了 停電了嗎???"}, {"comment_author": "Mradult", "comment_date": ["04/15", "22:18"], "comment_content": "是有停了嗎？沒有就是韌性電網大成功"}, {"comment_author": "babosa633", "comment_date": ["04/15", "22:18"], "comment_content": "冷氣該全開了"}, {"comment_author": "Plato12", "comment_date": ["04/15", "22:18"], "comment_content": "智障40%請別吹冷氣 非核家園 你家跳電"}, {"comment_author": "babosa633", "comment_date": ["04/15", "22:19"], "comment_content": "塔綠班冷氣+暖氣+窗戶全開，用愛發電"}, {"comment_author": "kj632868", "comment_date": ["04/15", "22:19"], "comment_content": "這新聞在造謠吧 黨說不缺電欸"}, {"comment_author": "pro33342", "comment_date": ["04/15", "22:19"], "comment_content": "大家冷氣開起來"}, {"comment_author": "Plato12", "comment_date": ["04/15", "22:19"], "comment_content": "就是停電如何 哥布林又跑去躲嗎 還敢狗叫"}, {"comment_author": "frioandy", "comment_date": ["04/15", "22:20"], "comment_content": "藻礁被擋，核廢料放你家也不要，不知道"}, {"comment_author": "ILOVEluee", "comment_date": ["04/15", "22:20"], "comment_content": "等夏天來大停電  南部應該很爽"}, {"comment_author": "frioandy", "comment_date": ["04/15", "22:20"], "comment_content": "你們這群藍白要什麼"}, {"comment_author": "babosa633", "comment_date": ["04/15", "22:20"], "comment_content": "高雄優先關電，全台不缺電"}, {"comment_author": "flowersuger", "comment_date": ["04/15", "22:20"], "comment_content": "蛤 那今晚可以開冷氣嗎"}, {"comment_author": "chinjay2008", "comment_date": ["04/15", "22:20"], "comment_content": "漲電價是對的，上面有錢人多幫忙出"}, {"comment_author": "flowersuger", "comment_date": ["04/15", "22:21"], "comment_content": "開不開明天可能都沒電？"}, {"comment_author": "gucci3345678", "comment_date": ["04/15", "22:21"], "comment_content": "我決定今天冷氣開16度"}, {"comment_author": "babosa633", "comment_date": ["04/15", "22:21"], "comment_content": "南電中送，中電北送"}, {"comment_author": "lsmd", "comment_date": ["04/15", "22:21"], "comment_content": "火力運轉到超過100%真是猛"}, {"comment_author": "aerbercer", "comment_date": ["04/15", "22:22"], "comment_content": "40%： 世界跟不上台灣！"}, {"comment_author": "your0207", "comment_date": ["04/15", "22:24"], "comment_content": "基隆也有發電為什麼當時要計畫被停電"}, {"comment_author": "jack529", "comment_date": ["04/15", "22:25"], "comment_content": "核電又要來救了"}, {"comment_author": "sd90213", "comment_date": ["04/15", "22:26"], "comment_content": "喜迎停電做功德"}, {"comment_author": "DasonoMaso", "comment_date": ["04/15", "22:26"], "comment_content": "阿不是不缺電"}, {"comment_author": "eric0924", "comment_date": ["04/15", "22:26"], "comment_content": "冷氣開起來~~"}, {"comment_author": "tuanlin", "comment_date": ["04/15", "22:26"], "comment_content": "就真的不缺電啊"}, {"comment_author": "jamesmile", "comment_date": ["04/15", "22:28"], "comment_content": "臺灣不缺電的"}, {"comment_author": "lemondrink", "comment_date": ["04/15", "22:28"], "comment_content": "40%就愛這一味"}, {"comment_author": "foxvera", "comment_date": ["04/15", "22:28"], "comment_content": "怕三小，今晚太陽會為了黨的政績昇"}, {"comment_author": "foxvera", "comment_date": ["04/15", "22:28"], "comment_content": "起"}, {"comment_author": "s854273", "comment_date": ["04/15", "22:29"], "comment_content": "讚啦!冷氣開下去"}, {"comment_author": "k22941920", "comment_date": ["04/15", "22:29"], "comment_content": "還沒高峰就這樣 厲害了我的政府"}, {"comment_author": "banana781109", "comment_date": ["04/15", "22:29"], "comment_content": "鄭副院長麗君說台灣不缺電"}, {"comment_author": "arc332890", "comment_date": ["04/15", "22:31"], "comment_content": "垃圾民進党"}, {"comment_author": "binco", "comment_date": ["04/15", "22:31"], "comment_content": "哈哈四月就這樣。大家等著看夏天囉"}, {"comment_author": "powerworld21", "comment_date": ["04/15", "22:31"], "comment_content": "不用怕啦 降壓就好了 等等 該不會.."}, {"comment_author": "powerworld21", "comment_date": ["04/15", "22:31"], "comment_content": ".已經降壓了吧？"}, {"comment_author": "mithuang", "comment_date": ["04/15", "22:32"], "comment_content": "把地震能量拿來發電不是很好"}, {"comment_author": "SapphireNoah", "comment_date": ["04/15", "22:33"], "comment_content": "把南部沒貢獻的低端地區停掉就好啦"}, {"comment_author": "kakuson", "comment_date": ["04/15", "22:33"], "comment_content": "反正怎麼搞結果都是DPP勝選"}, {"comment_author": "EXUAN", "comment_date": ["04/15", "22:33"], "comment_content": "降壓不會有問題嗎？"}, {"comment_author": "jimlexus", "comment_date": ["04/15", "22:33"], "comment_content": "缺電？還是缺腦？"}, {"comment_author": "sw9294", "comment_date": ["04/15", "22:33"], "comment_content": "好了啦，黨就說不缺電了肯定有藏電"}, {"comment_author": "TETUO", "comment_date": ["04/15", "22:33"], "comment_content": "政治凌駕專業，部會首長都是磕頭應聲蟲，"}, {"comment_author": "TETUO", "comment_date": ["04/15", "22:33"], "comment_content": "都是國之將亡的跡象"}, {"comment_author": "kimfor", "comment_date": ["04/15", "22:34"], "comment_content": "不缺電，台電藏電"}, {"comment_author": "marke18", "comment_date": ["04/15", "22:34"], "comment_content": "亂說話測不準的沒究責 還升任副閣揆 天啊"}, {"comment_author": "ZIQQ001", "comment_date": ["04/15", "22:34"], "comment_content": "這天氣停電 會熱死"}, {"comment_author": "kimfor", "comment_date": ["04/15", "22:34"], "comment_content": "最好笑的是發生這麼多這些爛事"}, {"comment_author": "kimfor", "comment_date": ["04/15", "22:34"], "comment_content": "經濟部長穩穩地"}, {"comment_author": "Dean997", "comment_date": ["04/15", "22:34"], "comment_content": "電網才不會崩潰，不要造謠好嗎！"}, {"comment_author": "tonist9808", "comment_date": ["04/15", "22:35"], "comment_content": "以後年年缺水缺電，謝謝40%謝謝黨"}, {"comment_author": "ZIQQ001", "comment_date": ["04/15", "22:35"], "comment_content": ""}, {"comment_author": "SY082022", "comment_date": ["04/15", "22:35"], "comment_content": "政府說不缺電"}, {"comment_author": "kairiyu", "comment_date": ["04/15", "22:37"], "comment_content": "早就開冷氣了"}, {"comment_author": "TETUO", "comment_date": ["04/15", "22:37"], "comment_content": "不是缺電是電網韌性不足，需要更多預算改"}, {"comment_author": "TETUO", "comment_date": ["04/15", "22:37"], "comment_content": "善，不要唱衰台灣，民主第一品牌，美德台灣"}, {"comment_author": "wklxbiwee", "comment_date": ["04/15", "22:38"], "comment_content": "火力真可憐 好隊友被拔走 只能靠一群擺"}, {"comment_author": "birdskingla", "comment_date": ["04/15", "22:38"], "comment_content": "可悲"}, {"comment_author": "wklxbiwee", "comment_date": ["04/15", "22:38"], "comment_content": "爛的再生能源"}, {"comment_author": "rizalpiggy", "comment_date": ["04/15", "22:38"], "comment_content": "沒差 政府說不缺電 我冷氣就是要開爛"}, {"comment_author": "TKKYO", "comment_date": ["04/15", "22:38"], "comment_content": "40%真的要死趕快去死，不要拖累60%的人"}, {"comment_author": "flaneurbk", "comment_date": ["04/15", "22:38"], "comment_content": "台灣不缺電，不要造謠好嗎，冷氣開下"}, {"comment_author": "flaneurbk", "comment_date": ["04/15", "22:38"], "comment_content": "去，讚"}, {"comment_author": "riker729", "comment_date": ["04/15", "22:39"], "comment_content": "連水情吃緊的石門都用上...放掉就沒了耶"}, {"comment_author": "riker729", "comment_date": ["04/15", "22:39"], "comment_content": "結果缺水是因為缺電......"}, {"comment_author": "MLXG0103", "comment_date": ["04/15", "22:39"], "comment_content": "問就是沒缺電 造謠的三百萬準備好哦"}, {"comment_author": "a09162277", "comment_date": ["04/15", "22:40"], "comment_content": "先停南部好嗎 底層垃圾還是會支持"}, {"comment_author": "inuwanwan", "comment_date": ["04/15", "22:40"], "comment_content": "停電幫忙省電費,不好嗎"}, {"comment_author": "sunday0913", "comment_date": ["04/15", "22:41"], "comment_content": "是說藏電的那位要接副閣揆,你以後"}, {"comment_author": "sunday0913", "comment_date": ["04/15", "22:41"], "comment_content": "自己注意啊"}, {"comment_author": "TurtLeKwei", "comment_date": ["04/15", "22:41"], "comment_content": "又再恐嚇 先罰兩百萬 dpp說不缺電 哪"}, {"comment_author": "TurtLeKwei", "comment_date": ["04/15", "22:41"], "comment_content": "來的野雞記者"}, {"comment_author": "retrud", "comment_date": ["04/15", "22:42"], "comment_content": "我想開16度 但電費漲價沒錢 哭哭"}, {"comment_author": "sid3", "comment_date": ["04/15", "22:42"], "comment_content": "又不是沒全台大停電過  怕什麼"}, {"comment_author": "duCK106", "comment_date": ["04/15", "22:43"], "comment_content": "哇"}, {"comment_author": "Irelia56", "comment_date": ["04/15", "22:43"], "comment_content": "又再騙 党說不缺電欸"}, {"comment_author": "r51211214", "comment_date": ["04/15", "22:43"], "comment_content": "台電還在藏 怎麼可能缺電"}, {"comment_author": "ashinly1021", "comment_date": ["04/15", "22:44"], "comment_content": "40%快點做愛好嗎 要不夠電了"}, {"comment_author": "zeroBB", "comment_date": ["04/15", "22:44"], "comment_content": "選完了，其實大停電也沒差吧。"}, {"comment_author": "serrier", "comment_date": ["04/15", "22:44"], "comment_content": "少了水庫水力發電就缺電?那缺水怎麼辦?"}, {"comment_author": "serrier", "comment_date": ["04/15", "22:45"], "comment_content": "水庫都快缺水還在那邊水力發電?"}, {"comment_author": "serrier", "comment_date": ["04/15", "22:45"], "comment_content": "有些水庫水位過低根本不適合發電啊"}, {"comment_author": "serrier", "comment_date": ["04/15", "22:45"], "comment_content": "某人號稱電儲能系統這時候不拿出來用?"}, {"comment_author": "Irelia56", "comment_date": ["04/15", "22:47"], "comment_content": ""}, {"comment_author": "Ahsoy", "comment_date": ["04/15", "22:47"], "comment_content": "幹他媽的說不缺電的出來面對喔"}, {"comment_author": "degneva", "comment_date": ["04/15", "22:49"], "comment_content": "不是缺電 是最近大家的愛不夠"}, {"comment_author": "finalcoffee", "comment_date": ["04/15", "22:49"], "comment_content": "沒事兒40%都自主節約不用電"}, {"comment_author": "miforward", "comment_date": ["04/15", "22:51"], "comment_content": "40%請用愛驅動家裡電器好嗎，不要再用"}, {"comment_author": "miforward", "comment_date": ["04/15", "22:51"], "comment_content": "發電廠的電了"}, {"comment_author": "A80211ab", "comment_date": ["04/15", "22:51"], "comment_content": "那就停啊 自己愛選民進黨的"}, {"comment_author": "zick8932511", "comment_date": ["04/15", "22:51"], "comment_content": "然後呢 這幾年在幹嘛？綠能 笑死"}, {"comment_author": "zaqimon", "comment_date": ["04/15", "22:51"], "comment_content": "中國：我這邊有便宜穩定的核電趕快來買"}, {"comment_author": "WU3CO00J", "comment_date": ["04/15", "22:52"], "comment_content": "今年夏天一定很精彩！"}, {"comment_author": "Shadouie", "comment_date": ["04/15", "22:53"], "comment_content": "快拿出藏電啊 都要大停電了 還不拿出來"}, {"comment_author": "stayme", "comment_date": ["04/15", "22:55"], "comment_content": "還敢漲電價啊"}, {"comment_author": "dayuer", "comment_date": ["04/15", "22:56"], "comment_content": "低能反核人士快上街靠盃核災唷XD"}, {"comment_author": "chulen", "comment_date": ["04/15", "22:56"], "comment_content": "漲電費還停啥小電?"}, {"comment_author": "b8806", "comment_date": ["04/15", "22:57"], "comment_content": "慶祝520登基"}, {"comment_author": "aa890051", "comment_date": ["04/15", "22:57"], "comment_content": "台積電繼續蓋"}, {"comment_author": "serrier", "comment_date": ["04/15", "22:57"], "comment_content": "王美花經濟部長這時候跑去哪?"}, {"comment_author": "ax162051", "comment_date": ["04/15", "22:58"], "comment_content": "不要怕 我們有綠電…幫忙賺錢"}, {"comment_author": "es612", "comment_date": ["04/15", "22:58"], "comment_content": "某立委:台電藏電"}, {"comment_author": "Thorvs", "comment_date": ["04/15", "22:58"], "comment_content": "經濟部明明說電網很強韌，儲能+綠能超猛"}, {"comment_author": "gustavvv", "comment_date": ["04/15", "23:00"], "comment_content": "先停南部的"}, {"comment_author": "jewish123", "comment_date": ["04/15", "23:00"], "comment_content": "爽 冷氣16度開起來"}, {"comment_author": "Qualaa", "comment_date": ["04/15", "23:00"], "comment_content": "用愛發電怎麼會缺電 不懂"}, {"comment_author": "jaredex02", "comment_date": ["04/15", "23:01"], "comment_content": "藏電啦"}, {"comment_author": "leeroy277", "comment_date": ["04/15", "23:01"], "comment_content": "好的追加預算買綠電"}, {"comment_author": "patrick123", "comment_date": ["04/15", "23:02"], "comment_content": "絕對不會缺電假新聞"}, {"comment_author": "holisong5566", "comment_date": ["04/15", "23:03"], "comment_content": "這樣叫不缺電 蒸蚌"}, {"comment_author": "snoopyconnie", "comment_date": ["04/15", "23:03"], "comment_content": "笑死"}, {"comment_author": "wei9898", "comment_date": ["04/15", "23:04"], "comment_content": "冷氣18度開下去"}, {"comment_author": "t81511270", "comment_date": ["04/15", "23:05"], "comment_content": "40% 在那邊吹 地震還好前沾"}, {"comment_author": "jerry840622", "comment_date": ["04/15", "23:05"], "comment_content": "有人藏電 趕快抓出來是誰"}, {"comment_author": "Bmtswiiii", "comment_date": ["04/15", "23:06"], "comment_content": "退役的重新啟動是退好玩的是不是"}, {"comment_author": "stephon50", "comment_date": ["04/15", "23:06"], "comment_content": "中共不用打 台灣就被塔綠班搞倒了"}, {"comment_author": "wdouglas", "comment_date": ["04/15", "23:07"], "comment_content": "看來那些除役的機組以後都變緊急應用機"}, {"comment_author": "wdouglas", "comment_date": ["04/15", "23:07"], "comment_content": "組"}, {"comment_author": "iorih0304", "comment_date": ["04/15", "23:07"], "comment_content": "樓下說半夜可以抽水上去回水庫"}, {"comment_author": "alexjeter", "comment_date": ["04/15", "23:08"], "comment_content": "垃圾40%"}, {"comment_author": "mcyangtw", "comment_date": ["04/15", "23:08"], "comment_content": "16度？顯然電價太便宜了"}, {"comment_author": "angelafreet", "comment_date": ["04/15", "23:09"], "comment_content": "以前從來沒想過要買UPS這幾年停電停"}, {"comment_author": "angelafreet", "comment_date": ["04/15", "23:09"], "comment_content": "到怕了馬上買了一台UPS以防萬一"}, {"comment_author": "strams", "comment_date": ["04/15", "23:09"], "comment_content": "第三世界國家"}, {"comment_author": "Bmtswiiii", "comment_date": ["04/15", "23:09"], "comment_content": "之前吹綠能的爵青勒，死了是不是怎麼"}, {"comment_author": "Bmtswiiii", "comment_date": ["04/15", "23:09"], "comment_content": "這麼安靜？講話啊"}, {"comment_author": "liusean", "comment_date": ["04/15", "23:10"], "comment_content": "哥布林的綠能毫無作用"}, {"comment_author": "Irelia56", "comment_date": ["04/15", "23:11"], "comment_content": ""}, {"comment_author": "ya123456789", "comment_date": ["04/15", "23:11"], "comment_content": "真棒..40%還不關冷氣"}, {"comment_author": "wise0701", "comment_date": ["04/15", "23:13"], "comment_content": "好玩了，還沒夏天"}, {"comment_author": "kinyizi", "comment_date": ["04/15", "23:14"], "comment_content": "可憐啊，功率可以破一百趴，文組：那只直"}, {"comment_author": "kinyizi", "comment_date": ["04/15", "23:14"], "comment_content": "接飆到兩百，問題就解決了"}, {"comment_author": "zerowingtw", "comment_date": ["04/15", "23:14"], "comment_content": "開心，坐看民進黨政府繼續反核"}, {"comment_author": "owenfish", "comment_date": ["04/15", "23:14"], "comment_content": "乾我屁事 反正不缺電"}, {"comment_author": "acxsport", "comment_date": ["04/15", "23:15"], "comment_content": "那是民進黨的事，大家冷氣吹起來"}, {"comment_author": "Arashi0731", "comment_date": ["04/15", "23:17"], "comment_content": "兒子學校冷氣沒到夏天不能開，笑死"}, {"comment_author": "douxid", "comment_date": ["04/15", "23:17"], "comment_content": "嚇死我了冷氣再調低五度"}, {"comment_author": "JF5385", "comment_date": ["04/15", "23:18"], "comment_content": "wow"}, {"comment_author": "br06", "comment_date": ["04/15", "23:19"], "comment_content": "當初要不是環境流氓潘老師..."}, {"comment_author": "QB6996", "comment_date": ["04/15", "23:19"], "comment_content": "缺電就叫大家點蠟燭啊，你各位低產值低貢"}, {"comment_author": "QB6996", "comment_date": ["04/15", "23:20"], "comment_content": "獻的沒資格用電，反正台灣只要科技園區有"}, {"comment_author": "QB6996", "comment_date": ["04/15", "23:20"], "comment_content": "點就能活。"}, {"comment_author": "lastphil", "comment_date": ["04/15", "23:20"], "comment_content": "沒電就老招停高雄的電就好了 根本沒差"}, {"comment_author": "Ron51320", "comment_date": ["04/15", "23:20"], "comment_content": "賴慘了，爛攤子都他的，呵"}, {"comment_author": "testes", "comment_date": ["04/15", "23:20"], "comment_content": "嚇死我了 今晚冷氣開17度幫幫政府好了"}, {"comment_author": "fju0911", "comment_date": ["04/15", "23:24"], "comment_content": "党說夠！"}, {"comment_author": "oswin", "comment_date": ["04/15", "23:25"], "comment_content": "明天又要做圖卡騙人了，死光頭"}, {"comment_author": "tf010714", "comment_date": ["04/15", "23:26"], "comment_content": "怕啥 黨說夠就是夠 冷氣吹爆"}, {"comment_author": "devicer", "comment_date": ["04/15", "23:26"], "comment_content": "党說不缺電 不缺是在怕個屁"}, {"comment_author": "hitmd", "comment_date": ["04/15", "23:26"], "comment_content": "沒有缺點 嘻嘻"}, {"comment_author": "lujou", "comment_date": ["04/15", "23:28"], "comment_content": "又不缺電 不要吵好嗎"}, {"comment_author": "a1e", "comment_date": ["04/15", "23:28"], "comment_content": "才4月就這樣，六月限電就好笑了"}, {"comment_author": "SHINNOIZUMI", "comment_date": ["04/15", "23:30"], "comment_content": "有些人就是不見棺材不掉淚，來個大"}, {"comment_author": "SHINNOIZUMI", "comment_date": ["04/15", "23:30"], "comment_content": "停電讓人民痛，某些人才會醒"}, {"comment_author": "aoyama", "comment_date": ["04/15", "23:30"], "comment_content": "把藏電 找粗乃呀"}, {"comment_author": "yufat", "comment_date": ["04/15", "23:30"], "comment_content": "遲早大停電 不要不信邪"}, {"comment_author": "dai26", "comment_date": ["04/15", "23:31"], "comment_content": "核三要停了，恭喜817求仁得仁"}, {"comment_author": "fcz973", "comment_date": ["04/15", "23:32"], "comment_content": "不是缺電，是你們太浪費"}, {"comment_author": "rich780501", "comment_date": ["04/15", "23:34"], "comment_content": "樓下冷氣16°C預備！"}, {"comment_author": "HsuKathy", "comment_date": ["04/15", "23:34"], "comment_content": "不管啦 我們40%吹好吹滿 叫60%關冷氣"}, {"comment_author": "sincere77", "comment_date": ["04/15", "23:34"], "comment_content": "準副閣揆快把台電藏的電找出來好嗎"}, {"comment_author": "xu3ck", "comment_date": ["04/15", "23:35"], "comment_content": "中時欠黨告是不是？ 製造恐慌？"}, {"comment_author": "biostrike", "comment_date": ["04/15", "23:35"], "comment_content": "4月就沒電，789月死定了"}, {"comment_author": "kukuyo", "comment_date": ["04/15", "23:35"], "comment_content": "胡說八道又還沒停電 黨說沒事就沒事"}, {"comment_author": "VVii", "comment_date": ["04/15", "23:36"], "comment_content": "破麻母豬房間的冷氣關了沒"}, {"comment_author": "November1992", "comment_date": ["04/15", "23:38"], "comment_content": "還有一個月啊 喔no"}, {"comment_author": "EasyVinus", "comment_date": ["04/15", "23:38"], "comment_content": "綠色是草包的顏色"}, {"comment_author": "jesiuty", "comment_date": ["04/15", "23:39"], "comment_content": "缺水還水力發電 東南亞第一 黨的面子不能"}, {"comment_author": "jesiuty", "comment_date": ["04/15", "23:39"], "comment_content": "丟"}, {"comment_author": "k374318", "comment_date": ["04/15", "23:40"], "comment_content": "90%火力啦笑死人，難怪肺癌一堆"}, {"comment_author": "c24253994", "comment_date": ["04/15", "23:40"], "comment_content": "去斷40%電啊幹"}, {"comment_author": "c24253994", "comment_date": ["04/15", "23:40"], "comment_content": "支持投票實名制啦幹"}, {"comment_author": "aj064534", "comment_date": ["04/15", "23:41"], "comment_content": "中共同路人+1"}, {"comment_author": "ab566", "comment_date": ["04/15", "23:45"], "comment_content": "雲豹小公主救救台電"}, {"comment_author": "alan0204", "comment_date": ["04/15", "23:46"], "comment_content": "不缺電"}, {"comment_author": "suntw", "comment_date": ["04/15", "23:48"], "comment_content": "噓永和仔"}, {"comment_author": "zx610176", "comment_date": ["04/15", "23:49"], "comment_content": "到底要不要恢復核分裂發電啦 承認能源"}, {"comment_author": "EdgeGuy", "comment_date": ["04/15", "23:49"], "comment_content": "智障反核團體"}, {"comment_author": "zx610176", "comment_date": ["04/15", "23:49"], "comment_content": "政策大失敗很難嗎"}, {"comment_author": "stevenpiglin", "comment_date": ["04/15", "23:51"], "comment_content": "做愛發電啊"}, {"comment_author": "fundme", "comment_date": ["04/15", "23:52"], "comment_content": "台電有沒有藏電 有沒有私房電？"}, {"comment_author": "realmarmot", "comment_date": ["04/15", "23:53"], "comment_content": "誰在藏電 把電拿出來"}, {"comment_author": "Ultramarine", "comment_date": ["04/15", "23:55"], "comment_content": "又再藏"}, {"comment_author": "andy199113", "comment_date": ["04/15", "23:57"], "comment_content": "支持核能發電 建設SMR小型核電廠!"}, {"comment_author": "andy199113", "comment_date": ["04/15", "23:57"], "comment_content": "賣台蔡英文該抓去監獄關到死"}, {"comment_author": "boloz", "comment_date": ["04/15", "23:57"], "comment_content": "再撐一下，等鄭麗君上台就會把台電藏的電拿"}, {"comment_author": "boloz", "comment_date": ["04/15", "23:57"], "comment_content": "出來"}, {"comment_author": "Number9527", "comment_date": ["04/15", "23:58"], "comment_content": "政府說不缺 就是不缺   懂不？！"}, {"comment_author": "wulaw5566", "comment_date": ["04/15", "23:59"], "comment_content": "請鄭麗君找出台電藏的電"}, {"comment_author": "iverson414", "comment_date": ["04/15", "23:59"], "comment_content": "沒缺電因為垃圾們都大賺錢"}, {"comment_author": "dreamaki", "comment_date": ["04/15", "23:59"], "comment_content": "斷40%的電就好啦，跟黨一樣自慰，用愛發"}, {"comment_author": "dreamaki", "comment_date": ["04/15", "23:59"], "comment_content": "電就好"}, {"comment_author": "nigue", "comment_date": ["04/16", "00:01"], "comment_content": "蔡英文弄爛台灣"}, {"comment_author": "YOLOO", "comment_date": ["04/16", "00:02"], "comment_content": "夏天還沒到就快停電囉 嘻嘻"}, {"comment_author": "soarling", "comment_date": ["04/16", "00:02"], "comment_content": "反正沒電就臭罵你們台電祖宗18代 就是這"}, {"comment_author": "e8907088", "comment_date": ["04/16", "00:02"], "comment_content": "文章寫錯一些 那不是超額運轉 還有幾趴"}, {"comment_author": "soarling", "comment_date": ["04/16", "00:02"], "comment_content": "麼簡單"}, {"comment_author": "e8907088", "comment_date": ["04/16", "00:02"], "comment_content": "那個不是功率 是負載啪數"}, {"comment_author": "pida5566", "comment_date": ["04/16", "00:04"], "comment_content": "關我屁事 不是不缺電嗎 40%用愛發電阿"}, {"comment_author": "letbeit", "comment_date": ["04/16", "00:05"], "comment_content": "沒關係，就是要痛過才會改"}, {"comment_author": "kkjjrtlym", "comment_date": ["04/16", "00:08"], "comment_content": "馬的垃圾不給蓋核能 又要台機炒房 噁心"}, {"comment_author": "Wx7621", "comment_date": ["04/16", "00:16"], "comment_content": "都還沒開冷氣就不足了 gg用的嗎"}, {"comment_author": "jason3151", "comment_date": ["04/16", "00:16"], "comment_content": "40%最好全部出來用愛發電喔"}, {"comment_author": "ganlinlau", "comment_date": ["04/16", "00:17"], "comment_content": "先開16度，到時候溫度可以撐到天亮"}, {"comment_author": "gogoapolo", "comment_date": ["04/16", "00:17"], "comment_content": "停那40%的電啊，反正他們用愛就好了"}, {"comment_author": "didi22lic", "comment_date": ["04/16", "00:17"], "comment_content": "不缺電 別擔心"}, {"comment_author": "s0920151048", "comment_date": ["04/16", "00:19"], "comment_content": "沒事 不缺電"}, {"comment_author": "hsupaijay", "comment_date": ["04/16", "00:27"], "comment_content": "不可質疑的党"}, {"comment_author": "ac8297q64885", "comment_date": ["04/16", "00:28"], "comment_content": "只要看到這種新聞，我的冷氣就是開"}, {"comment_author": "ac8297q64885", "comment_date": ["04/16", "00:29"], "comment_content": "好開滿24小時不斷"}, {"comment_author": "sarspieya521", "comment_date": ["04/16", "00:29"], "comment_content": "不是藏電？不要造謠喔"}, {"comment_author": "Kenneth10", "comment_date": ["04/16", "00:31"], "comment_content": "誰藏電 快拿出來好嗎"}, {"comment_author": "JASONGOAHEAD", "comment_date": ["04/16", "00:31"], "comment_content": "我記得前幾天不是才在吹噓儲能？"}, {"comment_author": "CloudVII", "comment_date": ["04/16", "00:35"], "comment_content": "還敢歲修 不是說不缺電繼續騙啊"}, {"comment_author": "Ron51320", "comment_date": ["04/16", "00:36"], "comment_content": "看來10月在漲一波電價？"}, {"comment_author": "n0bp6gjo3", "comment_date": ["04/16", "00:40"], "comment_content": "鄭麗君會找出台電藏的電"}, {"comment_author": "richard520", "comment_date": ["04/16", "00:42"], "comment_content": "誰藏電 快拿出來好嗎"}, {"comment_author": "Lukechao", "comment_date": ["04/16", "00:45"], "comment_content": "電都藏起來了啦"}, {"comment_author": "h25949", "comment_date": ["04/16", "00:47"], "comment_content": "造謠抓去關"}, {"comment_author": "saedn", "comment_date": ["04/16", "00:48"], "comment_content": "假新聞嗎？"}, {"comment_author": "josephbb65", "comment_date": ["04/16", "00:54"], "comment_content": "某些機組燃燒超過100%了 40%也不會覺"}, {"comment_author": "josephbb65", "comment_date": ["04/16", "00:54"], "comment_content": "得缺電啦 嘻嘻"}, {"comment_author": "q123212", "comment_date": ["04/16", "00:58"], "comment_content": "不足5%？這對綠共來說是省錢欸"}, {"comment_author": "deathbead", "comment_date": ["04/16", "00:58"], "comment_content": "我不信，政府說沒有缺電，把冷氣開到最"}, {"comment_author": "deathbead", "comment_date": ["04/16", "00:59"], "comment_content": "強"}, {"comment_author": "Yisai", "comment_date": ["04/16", "01:07"], "comment_content": "丸子"}, {"comment_author": "jason112333", "comment_date": ["04/16", "01:08"], "comment_content": "有政府～不怕！"}, {"comment_author": "BigPhoenix", "comment_date": ["04/16", "01:13"], "comment_content": "沒事 不缺電 政府說的"}, {"comment_author": "even2300471", "comment_date": ["04/16", "01:16"], "comment_content": "天災人禍，德不配位"}, {"comment_author": "alfa147", "comment_date": ["04/16", "01:18"], "comment_content": "用愛啊！"}, {"comment_author": "Litfal", "comment_date": ["04/16", "01:20"], "comment_content": "不缺電啦"}, {"comment_author": "sharkimage", "comment_date": ["04/16", "01:22"], "comment_content": "至少我們納稅養了雲豹"}, {"comment_author": "wei5730", "comment_date": ["04/16", "01:23"], "comment_content": "40%的應許之地 電不夠40%踩腳踏車發電"}, {"comment_author": "cloudpart2", "comment_date": ["04/16", "01:24"], "comment_content": "冷氣開下去"}, {"comment_author": "ledmstony", "comment_date": ["04/16", "01:26"], "comment_content": "到時候南部先停一停 反正死忠的"}, {"comment_author": "rocit", "comment_date": ["04/16", "01:26"], "comment_content": "600萬長照投票人 空調整天開好開滿"}, {"comment_author": "mustangccx", "comment_date": ["04/16", "01:31"], "comment_content": "沒用的太陽綠不能"}, {"comment_author": "AirFuckKing", "comment_date": ["04/16", "01:31"], "comment_content": "沒事啦 不是有藏電 該拿出來了吧"}, {"comment_author": "a1234shin", "comment_date": ["04/16", "01:32"], "comment_content": "明天只要陰天就要開天窗了"}, {"comment_author": "kkoo5888", "comment_date": ["04/16", "01:33"], "comment_content": "我想看狗官們踩腳踏車發電"}, {"comment_author": "rakuinn", "comment_date": ["04/16", "01:34"], "comment_content": "綠電賺起來 吹給他跳電"}, {"comment_author": "imhan705", "comment_date": ["04/16", "01:34"], "comment_content": "穩啦 總統都跟你保證不缺了 開下去就對"}, {"comment_author": "imhan705", "comment_date": ["04/16", "01:35"], "comment_content": "了 難道總統會騙人嗎"}, {"comment_author": "Jaygo5566", "comment_date": ["04/16", "01:44"], "comment_content": "可以只停南部死忠仔的電嗎？幹"}, {"comment_author": "su35p2ul3", "comment_date": ["04/16", "01:49"], "comment_content": "文組的當政治人物的下場"}, {"comment_author": "kiyomaro", "comment_date": ["04/16", "01:50"], "comment_content": "超期待全台大停電的拉"}, {"comment_author": "cocogg", "comment_date": ["04/16", "01:52"], "comment_content": "還沒夏天呢=="}, {"comment_author": "ededed", "comment_date": ["04/16", "01:56"], "comment_content": "wow"}, {"comment_author": "cloud0528", "comment_date": ["04/16", "01:56"], "comment_content": "唉，可悲能源政策"}, {"comment_author": "sheep0121", "comment_date": ["04/16", "02:00"], "comment_content": "反核仔：不然核廢料放你家嗎？"}, {"comment_author": "sheep0121", "comment_date": ["04/16", "02:01"], "comment_content": "美國有零元購，台灣有用愛發電"}, {"comment_author": "sheep0121", "comment_date": ["04/16", "02:02"], "comment_content": "財團都急了，想著要自己蓋核電，就40趴"}, {"comment_author": "sheep0121", "comment_date": ["04/16", "02:03"], "comment_content": "低端還在靠北核廢料放你家"}, {"comment_author": "jackie0804", "comment_date": ["04/16", "02:04"], "comment_content": "白痴能源政策"}, {"comment_author": "yugi2567", "comment_date": ["04/16", "02:05"], "comment_content": "好我要開冷氣了"}, {"comment_author": "sparta40", "comment_date": ["04/16", "02:06"], "comment_content": "還沒到六七月 我們在等大趴踢"}, {"comment_author": "leokidd1976", "comment_date": ["04/16", "02:12"], "comment_content": "推"}, {"comment_author": "Tomberd", "comment_date": ["04/16", "02:21"], "comment_content": "停了嗎 在那叫什麼"}, {"comment_author": "lagidog", "comment_date": ["04/16", "02:33"], "comment_content": "開冷氣開冷氣"}, {"comment_author": "TOCIBS", "comment_date": ["04/16", "02:34"], "comment_content": "幹 你們不要一直笑政府啦 等等禁冷氣怎模"}, {"comment_author": "TOCIBS", "comment_date": ["04/16", "02:34"], "comment_content": "辦"}, {"comment_author": "cat654231", "comment_date": ["04/16", "02:42"], "comment_content": "冷氣已開兩個禮拜沒關"}, {"comment_author": "cat654231", "comment_date": ["04/16", "02:42"], "comment_content": "政府說不缺電好安心"}, {"comment_author": "wirecut", "comment_date": ["04/16", "03:26"], "comment_content": "我們還有風電跟太陽能哦"}, {"comment_author": "pccheni", "comment_date": ["04/16", "03:27"], "comment_content": "40%出來該兩聲，操你媽的！"}, {"comment_author": "menchian", "comment_date": ["04/16", "03:53"], "comment_content": "今年春天雨下這麼少，還在瘋狂用水力？"}, {"comment_author": "ooeamoo", "comment_date": ["04/16", "04:20"], "comment_content": "期待夏天到來"}, {"comment_author": "ccw2013", "comment_date": ["04/16", "04:21"], "comment_content": "死忠前陣子還在吹，根本垃圾整天騙"}, {"comment_author": "hohohoha", "comment_date": ["04/16", "05:39"], "comment_content": "沒事兒可以跟企業高價購電應急xd"}, {"comment_author": "alfahsu", "comment_date": ["04/16", "05:57"], "comment_content": "民進黨：台灣不缺電，我們做愛發電"}, {"comment_author": "MOBOI", "comment_date": ["04/16", "06:09"], "comment_content": "我一直相信政府說不缺電 冷氣我都開16。"}, {"comment_author": "kiddnash", "comment_date": ["04/16", "06:21"], "comment_content": "果然儲能指得是水力發電…"}, {"comment_author": "wryyyyyyyy", "comment_date": ["04/16", "06:22"], "comment_content": "花瓶部長最愛吹的"}, {"comment_author": "ilovebig99", "comment_date": ["04/16", "06:23"], "comment_content": "家裡有錢或有維生設施的，這幾天最好"}, {"comment_author": "ilovebig99", "comment_date": ["04/16", "06:23"], "comment_content": "把發電機準備好，機組故障應該沒那麼"}, {"comment_author": "ilovebig99", "comment_date": ["04/16", "06:23"], "comment_content": "快修好"}, {"comment_author": "ichiroyap", "comment_date": ["04/16", "06:29"], "comment_content": ""}, {"comment_author": "mhnl", "comment_date": ["04/16", "06:53"], "comment_content": "拿水補電，要缺水了"}, {"comment_author": "movi", "comment_date": ["04/16", "06:58"], "comment_content": "綠電穩的啦"}, {"comment_author": "zangif", "comment_date": ["04/16", "07:04"], "comment_content": "中介法有通過的話就可以直接刪除這篇新聞"}, {"comment_author": "zangif", "comment_date": ["04/16", "07:05"], "comment_content": "了"}, {"comment_author": "aoyama", "comment_date": ["04/16", "07:13"], "comment_content": "所以呢？ 有缺電造成停電嗎 垃圾新聞 嘻嘻"}, {"comment_author": "hoho5410", "comment_date": ["04/16", "07:16"], "comment_content": "塔綠班低能兒"}, {"comment_author": "azcooper", "comment_date": ["04/16", "07:23"], "comment_content": "不信谣不传谣"}, {"comment_author": "DennyXu", "comment_date": ["04/16", "07:31"], "comment_content": "黨說不缺電"}, {"comment_author": "rambo2728", "comment_date": ["04/16", "07:37"], "comment_content": "風力跟太陽能呢？唷原來是沒風的傍晚啊"}, {"comment_author": "GaryXie", "comment_date": ["04/16", "07:41"], "comment_content": "40%的選擇"}, {"comment_author": "Thor1230", "comment_date": ["04/16", "07:45"], "comment_content": "不用打戰擋台灣自己內耗就好"}, {"comment_author": "Fezico", "comment_date": ["04/16", "08:07"], "comment_content": "不信謠不傳謠，党說電力很多很夠用。冷氣1"}, {"comment_author": "Fezico", "comment_date": ["04/16", "08:07"], "comment_content": "6度開起來證明党是對的"}, {"comment_author": "qooggyy", "comment_date": ["04/16", "08:10"], "comment_content": "智障綠營：一定有人藏電，不然你問大小姐"}, {"comment_author": "ericthree", "comment_date": ["04/16", "08:12"], "comment_content": "黨說了不缺電 欠洗滌?"}, {"comment_author": "dodobaho", "comment_date": ["04/16", "08:13"], "comment_content": "晶圓廠蓋滿 冷氣吹滿 但不要核電 捉I發"}, {"comment_author": "GodBoneQ", "comment_date": ["04/16", "08:13"], "comment_content": "不用給發電給40%，牠們最會用愛發電"}, {"comment_author": "dodobaho", "comment_date": ["04/16", "08:13"], "comment_content": "電"}, {"comment_author": "show9202", "comment_date": ["04/16", "08:16"], "comment_content": "怎麼可能停電，又是藍白紅在造謠了"}, {"comment_author": "kuyfd456", "comment_date": ["04/16", "08:21"], "comment_content": "一定有人藏電"}, {"comment_author": "salamender", "comment_date": ["04/16", "08:22"], "comment_content": "推綠能的垃圾昆蟲呢"}, {"comment_author": "s008866", "comment_date": ["04/16", "08:31"], "comment_content": "不是還有電 缺了嗎"}, {"comment_author": "aaayukiaaa", "comment_date": ["04/16", "08:41"], "comment_content": "這次換什麼動物？"}, {"comment_author": "lyxiang", "comment_date": ["04/16", "08:45"], "comment_content": "欸，奉勸台電不要再藏電了喔，快拿出來"}, {"comment_author": "OLDBOY", "comment_date": ["04/16", "08:47"], "comment_content": "今天冷氣17度開起來"}, {"comment_author": "aowen", "comment_date": ["04/16", "08:47"], "comment_content": "飯盒優先停電 看你還有沒有愛"}, {"comment_author": "koyo017", "comment_date": ["04/16", "08:48"], "comment_content": "反正有40的不在乎"}, {"comment_author": "nailo71", "comment_date": ["04/16", "08:55"], "comment_content": "超過100% XD"}, {"comment_author": "fallennrise", "comment_date": ["04/16", "09:01"], "comment_content": "再給民進黨執政幾年台灣自己就垮了"}, {"comment_author": "fallennrise", "comment_date": ["04/16", "09:02"], "comment_content": "根本不用開戰搞爛台灣中國就統一了"}, {"comment_author": "lomeoh", "comment_date": ["04/16", "09:09"], "comment_content": "先對40趴死忠仔限電"}, {"comment_author": "kkkandy", "comment_date": ["04/16", "09:15"], "comment_content": "沒關係，40%投票都贏了，60%還能怎樣"}, {"comment_author": "kkkandy", "comment_date": ["04/16", "09:16"], "comment_content": "民進黨可以繼續爽四年，4年後人民就忘了"}, {"comment_author": "WarIII", "comment_date": ["04/16", "09:17"], "comment_content": "台電別藏了 藏的電還不交出來 這下藏不了"}, {"comment_author": "WarIII", "comment_date": ["04/16", "09:17"], "comment_content": "吧 哈哈哈哈"}, {"comment_author": "yzhna", "comment_date": ["04/16", "09:20"], "comment_content": "有個建議 要停水停電先停那40%"}, {"comment_author": "zanarland", "comment_date": ["04/16", "09:20"], "comment_content": "中共還沒來民進黨先把台灣搞垮"}, {"comment_author": "ChenDotQ", "comment_date": ["04/16", "09:30"], "comment_content": "惡政禍害子孫"}, {"comment_author": "hegemon", "comment_date": ["04/16", "09:35"], "comment_content": "民進黨會學到教訓現在台灣就不會是這副鳥"}, {"comment_author": "hegemon", "comment_date": ["04/16", "09:35"], "comment_content": "樣了"}, {"comment_author": "winterjoker", "comment_date": ["04/16", "09:46"], "comment_content": ""}, {"comment_author": "ada741116", "comment_date": ["04/16", "10:04"], "comment_content": "台灣不缺電，但是漲電價"}, {"comment_author": "blufish", "comment_date": ["04/16", "10:42"], "comment_content": "40%：缺水缺電還是缺腦？"}, {"comment_author": "orz151426", "comment_date": ["04/16", "11:05"], "comment_content": "蔡英文跟民進黨就是台灣最大災難"}, {"comment_author": "jaydenkoo", "comment_date": ["04/16", "12:39"], "comment_content": "十年不漲電價"}, {"comment_author": "XiaoKo484", "comment_date": ["04/16", "13:16"], "comment_content": "台電這麼努力發電 讓我更安心的吹冷氣"}, {"comment_author": "lose116315", "comment_date": ["04/16", "14:01"], "comment_content": "全台灣賠40%鑽木取火"}, {"comment_author": "Lolira", "comment_date": ["04/16", "16:44"], "comment_content": "裝睡的人"}, {"comment_author": "mf505", "comment_date": ["04/16", "19:17"], "comment_content": "問一下副閣揆，藏電去哪找"}, {"comment_author": "encoreg57985", "comment_date": ["04/16", "21:21"], "comment_content": "40%誤國"}]}
