{"author": "goetz (這世上還是有正義吧?)", "category": "Gossiping", "title": "Re: [新聞] 新加坡員工12月起可要求公司「週休3日」", "date": "Thu Apr 18 14:48:36 2024", "content": ["沒有什麼好羨慕的，我很久以前就有聽過一位X神的前輩這樣說:\"周休三日，工作量又沒有變成四天，該做的還不是要做?\"X神是國內很早實施周休三日的企業，不過後來還有沒有我就不知道了。所以實施周休三日，工作量是不是變成四天呢?還是依舊維持五天的量，只是這一天的量要在家裡做，或者攤在前面四天做完?這是一個很簡單的道理啊!--", "那還是一種壓榨啊...", "所以我才覺得本板有很多人不懂這個道理啊."], "post_comment": [{"comment_author": "SUMPO", "comment_date": ["04/18", "14:49"], "comment_content": "??....??哪來的奴隸"}, {"comment_author": "kuosambition", "comment_date": ["04/18", "14:49"], "comment_content": "所以才說是周休三日會提高工作效率"}, {"comment_author": "kuosambition", "comment_date": ["04/18", "14:51"], "comment_content": "壓縮你的工作時間，效率就擠出來了"}, {"comment_author": "kuosambition", "comment_date": ["04/18", "14:52"], "comment_content": "本來就是壓榨，你還真以為是為勞工"}, {"comment_author": "kuosambition", "comment_date": ["04/18", "14:52"], "comment_content": "著想阿~~換個說法虐待你而已XD"}, {"comment_author": "HolyBugTw", "comment_date": ["04/18", "14:53"], "comment_content": "你不能選延後一周作完嗎？"}, {"comment_author": "xxUno", "comment_date": ["04/18", "14:54"], "comment_content": "只是看哪個壓榨方法比較爽而已吧"}, {"comment_author": "Himiko9975", "comment_date": ["04/18", "14:54"], "comment_content": "原神"}, {"comment_author": "a77942002", "comment_date": ["04/18", "14:54"], "comment_content": "這個喔 我們可以推一週責任制 一天做完"}, {"comment_author": "a77942002", "comment_date": ["04/18", "14:54"], "comment_content": "就能休6天~"}, {"comment_author": "xxUno", "comment_date": ["04/18", "14:54"], "comment_content": "不然都是壓榨怎麼台灣企業就不敢三天"}, {"comment_author": "HolyBugTw", "comment_date": ["04/18", "14:54"], "comment_content": "一天幹完難道你能放假四天嗎？能選嗎？"}, {"comment_author": "jfw616", "comment_date": ["04/18", "15:03"], "comment_content": "一天就做完的工作...你會讓老闆發現嗎"}, {"comment_author": "HolyBugTw", "comment_date": ["04/18", "15:07"], "comment_content": "工作分派是leader又不是下屬的責任"}, {"comment_author": "veter", "comment_date": ["04/18", "15:16"], "comment_content": "想太多，你提前做完5天的工作量慣老闆會覺"}, {"comment_author": "veter", "comment_date": ["04/18", "15:16"], "comment_content": "得你太閒，下次就會給你double的量"}, {"comment_author": "veter", "comment_date": ["04/18", "15:17"], "comment_content": "所以當然是一天的工作量分一個禮拜做啊"}, {"comment_author": "HolyBugTw", "comment_date": ["04/18", "15:18"], "comment_content": "慣老闆是根本沒管什麼叫做工作量好嗎"}, {"comment_author": "HolyBugTw", "comment_date": ["04/18", "15:18"], "comment_content": "管你周休幾日他都覺得你要加班"}, {"comment_author": "HolyBugTw", "comment_date": ["04/18", "15:19"], "comment_content": "慣老闆只有deadline，還有要提早完成"}, {"comment_author": "HolyBugTw", "comment_date": ["04/18", "15:20"], "comment_content": "一個人扛百人份？他會跑來慰勞一下"}, {"comment_author": "HolyBugTw", "comment_date": ["04/18", "15:20"], "comment_content": "辛苦了，我把你當親生兒子看，多加油"}, {"comment_author": "HolyBugTw", "comment_date": ["04/18", "15:21"], "comment_content": "只是他口誤了一個字：龜兒子"}, {"comment_author": "sellgd", "comment_date": ["04/18", "15:21"], "comment_content": "周休3日 比soho還爽 我要回去上班"}, {"comment_author": "HolyBugTw", "comment_date": ["04/18", "15:25"], "comment_content": "當員工要能忍吃鱉，領遮羞費懂嗎"}, {"comment_author": "HolyBugTw", "comment_date": ["04/18", "15:26"], "comment_content": "老闆只會暴怒遷怒逼加班，他回的去嗎？"}]}
